Workbook

Sheet Dep-Mun
A1: Amazonas | B1: Antioquia | C1: Arauca | D1: Archipiélago_De_San_Andrés | E1: Atlántico | F1: Bogotá_D.C. | G1: Bolívar | H1: Boyacá | I1: Caldas | J1: Caquetá | K1: Casanare | L1: Cauca | M1: Cesar | N1: Chocó | O1: Córdoba | P1: Cundinamarca | Q1: Guainía | R1: Guaviare | S1: Huila | T1: La_Guajira | U1: Magdalena | V1: Meta | W1: Nariño | X1: Norte_De_Santander | Y1: Putumayo | Z1: Quindío | AA1: Risaralda | AB1: Santander | AC1: Sucre | AD1: Tolima | AE1: Valle_Del_Cauca | AF1: Vaupés | AG1: Vichada
A2: El Encanto | B2: Medellín | C2: Arauca | D2: San Andrés | E2: Barranquilla | F2: Bogotá, D.C. | G2: Cartagena De Indias | H2: Tunja | I2: Manizales | J2: Florencia | K2: Yopal | L2: Popayán | M2: Valledupar | N2: Quibdó | O2: Montería | P2: Agua De Dios | Q2: San Felipe | R2: San José Del Guaviare | S2: Neiva | T2: Riohacha | U2: Santa Marta | V2: Villavicencio | W2: Pasto | X2: San José De Cúcuta | Y2: Mocoa | Z2: Armenia | AA2: Pereira | AB2: Bucaramanga | AC2: Sincelejo | AD2: Ibagué | AE2: Santiago De Cali | AF2: Pacoa | AG2: Puerto Carreño
A3: La Chorrera | B3: Abejorral | C3: Arauquita | D3: Providencia | E3: Baranoa | G3: Achí | H3: Almeida | I3: Aguadas | J3: Albania | K3: Aguazul | L3: Almaguer | M3: Aguachica | N3: Acandí | O3: Ayapel | P3: Albán | Q3: Puerto Colombia | R3: Calamar | S3: Acevedo | T3: Albania | U3: Algarrobo | V3: Acacías | W3: Albán | X3: Ábrego | Y3: Colón | Z3: Buenavista | AA3: Apía | AB3: Aguada | AC3: Buenavista | AD3: Alpujarra | AE3: Alcalá | AF3: Papunahua | AG3: La Primavera
A4: La Pedrera | B4: Abriaquí | C4: Cravo Norte | E4: Campo De La Cruz | G4: Altos Del Rosario | H4: Aquitania | I4: Anserma | J4: Belén De Los Andaquíes | K4: Chámeza | L4: Argelia | M4: Agustín Codazzi | N4: Alto Baudó | O4: Buenavista | P4: Anapoima | Q4: La Guadalupe | R4: El Retorno | S4: Agrado | T4: Barrancas | U4: Aracataca | V4: Barranca De Upía | W4: Aldana | X4: Arboledas | Y4: Orito | Z4: Calarcá | AA4: Balboa | AB4: Albania | AC4: Caimito | AD4: Alvarado | AE4: Andalucía | AF4: Yavaraté | AG4: Santa Rosalía
A5: La Victoria | B5: Alejandría | C5: Fortul | E5: Candelaria | G5: Arenal | H5: Arcabuco | I5: Aranzazu | J5: Cartagena Del Chairá | K5: Hato Corozal | L5: Balboa | M5: Astrea | N5: Atrato | O5: Canalete | P5: Anolaima | Q5: Cacahual | R5: Miraflores | S5: Aipe | T5: Dibulla | U5: Ariguaní | V5: Cabuyaro | W5: Ancuya | X5: Bochalema | Y5: Puerto Asís | Z5: Circasia | AA5: Belén De Umbría | AB5: Aratoca | AC5: Colosó | AD5: Ambalema | AE5: Ansermanuevo | AF5: Mitú | AG5: Cumaribo
A6: Mirití - Paraná | B6: Amagá | C6: Puerto Rondón | E6: Galapa | G6: Arjona | H6: Belén | I6: Belalcázar | J6: Curillo | K6: La Salina | L6: Bolívar | M6: Becerril | N6: Bagadó | O6: Cereté | P6: Arbeláez | Q6: Pana Pana | S6: Algeciras | T6: Distracción | U6: Cerro De San Antonio | V6: Castilla La Nueva | W6: Arboleda | X6: Bucarasica | Y6: Puerto Caicedo | Z6: Córdoba | AA6: Dosquebradas | AB6: Barbosa | AC6: Corozal | AD6: Anzoátegui | AE6: Argelia | AF6: Carurú
A7: Puerto Alegría | B7: Amalfi | C7: Saravena | E7: Juan De Acosta | G7: Arroyohondo | H7: Berbeo | I7: Chinchiná | J7: El Doncello | K7: Maní | L7: Buenos Aires | M7: Bosconia | N7: Bahía Solano | O7: Chimá | P7: Beltrán | Q7: Morichal | S7: Altamira | T7: El Molino | U7: Chivolo | V7: Cubarral | W7: Barbacoas | X7: Cácota | Y7: Puerto Guzmán | Z7: Filandia | AA7: Guática | AB7: Barichara | AC7: Coveñas | AD7: Armero | AE7: Bolívar | AF7: Taraira
A8: Puerto Arica | B8: Andes | C8: Tame | E8: Luruaco | G8: Barranco De Loba | H8: Betéitiva | I8: Filadelfia | J8: El Paujíl | K8: Monterrey | L8: Cajibío | M8: Chimichagua | N8: Bajo Baudó | O8: Chinú | P8: Bituima | Q8: Inírida | S8: Baraya | T8: Fonseca | U8: Ciénaga | V8: Cumaral | W8: Belén | X8: Cáchira | Y8: Puerto Leguízamo | Z8: Génova | AA8: La Celia | AB8: Barrancabermeja | AC8: Chalán | AD8: Ataco | AE8: Buenaventura
A9: Puerto Santander | B9: Angelópolis | E9: Malambo | G9: Calamar | H9: Boavita | I9: La Dorada | J9: La Montañita | K9: Nunchía | L9: Caldono | M9: Chiriguaná | N9: Bojayá | O9: Ciénaga De Oro | P9: Bojacá | Q9: Barrancominas | S9: Campoalegre | T9: Hatonuevo | U9: Concordia | V9: El Calvario | W9: Buesaco | X9: Chinácota | Y9: Sibundoy | Z9: La Tebaida | AA9: La Virginia | AB9: Betulia | AC9: El Roble | AD9: Cajamarca | AE9: Guadalajara De Buga
A10: Tarapacá | B10: Angostura | E10: Manatí | G10: Cantagallo | H10: Boyacá | I10: La Merced | J10: Milán | K10: Orocué | L10: Caloto | M10: Curumaní | N10: El Cantón Del San Pablo | O10: Cotorra | P10: Cabrera | S10: Colombia | T10: La Jagua Del Pilar | U10: El Banco | V10: El Castillo | W10: Colón | X10: Chitagá | Y10: San Francisco | Z10: Montenegro | AA10: Marsella | AB10: Bolívar | AC10: Galeras | AD10: Carmen De Apicalá | AE10: Bugalagrande
A11: Leticia | B11: Anorí | E11: Palmar De Varela | G11: Cicuco | H11: Briceño | I11: Manzanares | J11: Morelia | K11: Paz De Ariporo | L11: Corinto | M11: El Copey | N11: Carmen Del Darién | O11: La Apartada | P11: Cachipay | S11: Elías | T11: Maicao | U11: El Piñón | V11: El Dorado | W11: Consacá | X11: Convención | Y11: San Miguel | Z11: Pijao | AA11: Mistrató | AB11: Cabrera | AC11: Guaranda | AD11: Casabianca | AE11: Caicedonia
A12: Puerto Nariño | B12: Santa Fé De Antioquia | E12: Piojó | G12: Córdoba | H12: Buenavista | I12: Marmato | J12: Puerto Rico | K12: Pore | L12: El Tambo | M12: El Paso | N12: Cértegui | O12: Lorica | P12: Cajicá | S12: Garzón | T12: Manaure | U12: El Retén | V12: Fuente De Oro | W12: Contadero | X12: Cucutilla | Y12: Santiago | Z12: Quimbaya | AA12: Pueblo Rico | AB12: California | AC12: La Unión | AD12: Chaparral | AE12: Calima
B13: Anzá | E13: Polonuevo | G13: Clemencia | H13: Busbanzá | I13: Marquetalia | J13: San José Del Fragua | K13: Recetor | L13: Florencia | M13: Gamarra | N13: Condoto | O13: Los Córdobas | P13: Caparrapí | S13: Gigante | T13: San Juan Del Cesar | U13: Fundación | V13: Granada | W13: Córdoba | X13: Durania | Y13: Valle Del Guamuez | Z13: Salento | AA13: Quinchía | AB13: Capitanejo | AC13: Los Palmitos | AD13: Coello | AE13: Candelaria
B14: Apartadó | E14: Ponedera | G14: El Carmen De Bolívar | H14: Caldas | I14: Marulanda | J14: San Vicente Del Caguán | K14: Sabanalarga | L14: Guachené | M14: González | N14: El Carmen De Atrato | O14: Momil | P14: Cáqueza | S14: Guadalupe | T14: Uribia | U14: Guamal | V14: Guamal | W14: Cuaspud Carlosama | X14: El Carmen | Y14: Villagarzón | AA14: Santa Rosa De Cabal | AB14: Carcasí | AC14: Majagual | AD14: Coyaima | AE14: Cartago
B15: Arboletes | E15: Puerto Colombia | G15: El Guamo | H15: Campohermoso | I15: Neira | J15: Solano | K15: Sácama | L15: Guapi | M15: La Gloria | N15: El Litoral Del San Juan | O15: Montelíbano | P15: Carmen De Carupa | S15: Hobo | T15: Urumita | U15: Nueva Granada | V15: Mapiripán | W15: Cumbal | X15: El Tarra | AA15: Santuario | AB15: Cepitá | AC15: Morroa | AD15: Cunday | AE15: Dagua
B16: Argelia | E16: Repelón | G16: El Peñón | H16: Cerinza | I16: Norcasia | J16: Solita | K16: San Luis De Palenque | L16: Inzá | M16: La Jagua De Ibirico | N16: Istmina | O16: Moñitos | P16: Chaguaní | S16: Íquira | T16: Villanueva | U16: Pedraza | V16: Mesetas | W16: Cumbitara | X16: El Zulia | AB16: Cerrito | AC16: Ovejas | AD16: Dolores | AE16: El Águila
B17: Armenia | E17: Sabanagrande | G17: Hatillo De Loba | H17: Chinavita | I17: Pácora | J17: Valparaíso | K17: Támara | L17: Jambaló | M17: Manaure Balcón Del Cesar | N17: Juradó | O17: Planeta Rica | P17: Chía | S17: Isnos | U17: Pijiño Del Carmen | V17: La Macarena | W17: Chachagüí | X17: Gramalote | AB17: Charalá | AC17: Palmito | AD17: Espinal | AE17: El Cairo
B18: Barbosa | E18: Sabanalarga | G18: Magangué | H18: Chiquinquirá | I18: Palestina | K18: Tauramena | L18: La Sierra | M18: Pailitas | N18: Lloró | O18: Pueblo Nuevo | P18: Chipaque | S18: La Argentina | U18: Pivijay | V18: Uribe | W18: El Charco | X18: Hacarí | AB18: Charta | AC18: Sampués | AD18: Falan | AE18: El Cerrito
B19: Belmira | E19: Santa Lucía | G19: Mahates | H19: Chiscas | I19: Pensilvania | K19: Trinidad | L19: La Vega | M19: Pelaya | N19: Medio Atrato | O19: Puerto Escondido | P19: Choachí | S19: La Plata | U19: Plato | V19: Lejanías | W19: El Peñol | X19: Herrán | AB19: Chima | AC19: San Benito Abad | AD19: Flandes | AE19: El Dovio
B20: Bello | E20: Santo Tomás | G20: Margarita | H20: Chita | I20: Riosucio | K20: Villanueva | L20: López De Micay | M20: Pueblo Bello | N20: Medio Baudó | O20: Puerto Libertador | P20: Chocontá | S20: Nátaga | U20: Puebloviejo | V20: Puerto Concordia | W20: El Rosario | X20: Labateca | AB20: Chipatá | AC20: San Juan De Betulia | AD20: Fresno | AE20: Florida
B21: Betania | E21: Soledad | G21: María La Baja | H21: Chitaraque | I21: Risaralda | L21: Mercaderes | M21: Río De Oro | N21: Medio San Juan | O21: Purísima De La Concepción | P21: Cogua | S21: Oporapa | U21: Remolino | V21: Puerto Gaitán | W21: El Tablón De Gómez | X21: La Esperanza | AB21: Cimitarra | AC21: San Marcos | AD21: Guamo | AE21: Ginebra
B22: Betulia | E22: Suan | G22: Montecristo | H22: Chivatá | I22: Salamina | L22: Miranda | M22: La Paz | N22: Nóvita | O22: Sahagún | P22: Cota | S22: Paicol | U22: Sabanas De San Ángel | V22: Puerto López | W22: El Tambo | X22: La Playa | AB22: Concepción | AC22: San Onofre | AD22: Herveo | AE22: Guacarí
B23: Ciudad Bolívar | E23: Tubará | G23: Santa Cruz De Mompox | H23: Ciénega | I23: Samaná | L23: Morales | M23: San Alberto | N23: Nuevo Belén De Bajirá * | O23: San Andrés De Sotavento | P23: Cucunubá | S23: Palermo | U23: Salamina | V23: Puerto Lleras | W23: Funes | X23: Los Patios | AB23: Confines | AC23: San Pedro | AD23: Honda | AE23: Jamundí
B24: Briceño | E24: Usiacurí | G24: Morales | H24: Cómbita | I24: San José | L24: Padilla | M24: San Diego | N24: Nuquí | O24: San Antero | P24: El Colegio | S24: Palestina | U24: San Sebastián De Buenavista | V24: Puerto Rico | W24: Guachucal | X24: Lourdes | AB24: Contratación | AC24: San Luis De Sincé | AD24: Icononzo | AE24: La Cumbre
B25: Buriticá | G25: Norosí | H25: Coper | I25: Supía | L25: Páez | M25: San Martín | N25: Río Iró | O25: San Bernardo Del Viento | P25: El Peñón | S25: Pital | U25: San Zenón | V25: Restrepo | W25: Guaitarilla | X25: Mutiscua | AB25: Coromoro | AC25: Sucre | AD25: Lérida | AE25: La Unión
B26: Cáceres | G26: Pinillos | H26: Corrales | I26: Victoria | L26: Patía | M26: Tamalameque | N26: Río Quito | O26: San Carlos | P26: El Rosal | S26: Pitalito | U26: Santa Ana | V26: San Carlos De Guaroa | W26: Gualmatán | X26: Ocaña | AB26: Curití | AC26: Santiago De Tolú | AD26: Líbano | AE26: La Victoria
B27: Caicedo | G27: Regidor | H27: Covarachía | I27: Villamaría | L27: Piamonte | N27: Riosucio | O27: San José De Uré | P27: Facatativá | S27: Rivera | U27: Santa Bárbara De Pinto | V27: San Juan De Arama | W27: Iles | X27: Pamplona | AB27: El Carmen De Chucurí | AC27: San José De Toluviejo | AD27: San Sebastián De Mariquita | AE27: Obando
B28: Caldas | G28: Río Viejo | H28: Cubará | I28: Viterbo | L28: Piendamó - Tunía | N28: San José Del Palmar | O28: San Pelayo | P28: Fómeque | S28: Saladoblanco | U28: Sitionuevo | V28: San Juanito | W28: Imués | X28: Pamplonita | AB28: El Guacamayo | AD28: Melgar | AE28: Palmira
B29: Campamento | G29: San Cristóbal | H29: Cucaita | L29: Puerto Tejada | N29: Sipí | O29: Tierralta | P29: Fosca | S29: San Agustín | U29: Tenerife | V29: San Martín | W29: Ipiales | X29: Puerto Santander | AB29: El Peñón | AD29: Murillo | AE29: Pradera
B30: Cañasgordas | G30: San Estanislao | H30: Cuítiva | L30: Puracé | N30: Tadó | O30: Tuchín | P30: Funza | S30: Santa María | U30: Zapayán | V30: Vistahermosa | W30: La Cruz | X30: Ragonvalia | AB30: El Playón | AD30: Natagaima | AE30: Restrepo
B31: Caracolí | G31: San Fernando | H31: Chíquiza | L31: Rosas | N31: Unguía | O31: Valencia | P31: Fúquene | S31: Suaza | U31: Zona Bananera | W31: La Florida | X31: Salazar | AB31: Encino | AD31: Ortega | AE31: Riofrío
B32: Caramanta | G32: San Jacinto | H32: Chivor | L32: San Sebastián | N32: Unión Panamericana | P32: Fusagasugá | S32: Tarqui | W32: La Llanada | X32: San Calixto | AB32: Enciso | AD32: Palocabildo | AE32: Roldanillo
B33: Carepa | G33: San Jacinto Del Cauca | H33: Duitama | L33: Santander De Quilichao | P33: Gachalá | S33: Tesalia | W33: La Tola | X33: San Cayetano | AB33: Florián | AD33: Piedras | AE33: San Pedro
B34: El Carmen De Viboral | G34: San Juan Nepomuceno | H34: El Cocuy | L34: Santa Rosa | P34: Gachancipá | S34: Tello | W34: La Unión | X34: Santiago | AB34: Floridablanca | AD34: Planadas | AE34: Sevilla
B35: Carolina | G35: San Martín De Loba | H35: El Espino | L35: Silvia | P35: Gachetá | S35: Teruel | W35: Leiva | X35: Sardinata | AB35: Galán | AD35: Prado | AE35: Toro
B36: Caucasia | G36: San Pablo | H36: Firavitoba | L36: Sotará Paispamba | P36: Gama | S36: Timaná | W36: Linares | X36: Silos | AB36: Gámbita | AD36: Purificación | AE36: Trujillo
B37: Chigorodó | G37: Santa Catalina | H37: Floresta | L37: Suárez | P37: Girardot | S37: Villavieja | W37: Los Andes | X37: Teorama | AB37: Girón | AD37: Rioblanco | AE37: Tuluá
B38: Cisneros | G38: Santa Rosa | H38: Gachantivá | L38: Sucre | P38: Granada | S38: Yaguará | W38: Magüí | X38: Tibú | AB38: Guaca | AD38: Roncesvalles | AE38: Ulloa
B39: Cocorná | G39: Santa Rosa Del Sur | H39: Gámeza | L39: Timbío | P39: Guachetá | W39: Mallama | X39: Toledo | AB39: Guadalupe | AD39: Rovira | AE39: Versalles
B40: Concepción | G40: Simití | H40: Garagoa | L40: Timbiquí | P40: Guaduas | W40: Mosquera | X40: Villa Caro | AB40: Guapotá | AD40: Saldaña | AE40: Vijes
B41: Concordia | G41: Soplaviento | H41: Guacamayas | L41: Toribío | P41: Guasca | W41: Nariño | X41: Villa Del Rosario | AB41: Guavatá | AD41: San Antonio | AE41: Yotoco
B42: Copacabana | G42: Talaigua Nuevo | H42: Guateque | L42: Totoró | P42: Guataquí | W42: Olaya Herrera | AB42: Güepsa | AD42: San Luis | AE42: Yumbo
B43: Dabeiba | G43: Tiquisio | H43: Guayatá | L43: Villa Rica | P43: Guatavita | W43: Ospina | AB43: Hato | AD43: Santa Isabel | AE43: Zarzal
B44: Donmatías | G44: Turbaco | H44: Güicán De La Sierra | P44: Guayabal De Síquima | W44: Francisco Pizarro | AB44: Jesús María | AD44: Suárez
B45: Ebéjico | G45: Turbana | H45: Iza | P45: Guayabetal | W45: Policarpa | AB45: Jordán | AD45: Valle De San Juan
B46: El Bagre | G46: Villanueva | H46: Jenesano | P46: Gutiérrez | W46: Potosí | AB46: La Belleza | AD46: Venadillo
B47: Entrerríos | G47: Zambrano | H47: Jericó | P47: Jerusalén | W47: Providencia | AB47: Landázuri | AD47: Villahermosa
B48: Envigado | H48: Labranzagrande | P48: Junín | W48: Puerres | AB48: La Paz | AD48: Villarrica
B49: Fredonia | H49: La Capilla | P49: La Calera | W49: Pupiales | AB49: Lebrija
B50: Frontino | H50: La Victoria | P50: La Mesa | W50: Ricaurte | AB50: Los Santos
B51: Giraldo | H51: La Uvita | P51: La Palma | W51: Roberto Payán | AB51: Macaravita
B52: Girardota | H52: Villa De Leyva | P52: La Peña | W52: Samaniego | AB52: Málaga
B53: Gómez Plata | H53: Macanal | P53: La Vega | W53: Sandoná | AB53: Matanza
B54: Granada | H54: Maripí | P54: Lenguazaque | W54: San Bernardo | AB54: Mogotes
B55: Guadalupe | H55: Miraflores | P55: Machetá | W55: San Lorenzo | AB55: Molagavita
B56: Guarne | H56: Mongua | P56: Madrid | W56: San Pablo | AB56: Ocamonte
B57: Guatapé | H57: Monguí | P57: Manta | W57: San Pedro De Cartago | AB57: Oiba
B58: Heliconia | H58: Moniquirá | P58: Medina | W58: Santa Bárbara | AB58: Onzaga
B59: Hispania | H59: Motavita | P59: Mosquera | W59: Santacruz | AB59: Palmar
B60: Itagüí | H60: Muzo | P60: Nariño | W60: Sapuyes | AB60: Palmas Del Socorro
... B65: La Estrella | H65: Pachavita | P65: Venecia | W65: Yacuanquer | AB65: Puerto Parra
B66: La Pintada | H66: Páez | P66: Pacho | AB66: Puerto Wilches
B67: La Unión | H67: Paipa | P67: Paime | AB67: Rionegro
B68: Liborina | H68: Pajarito | P68: Pandi | AB68: Sabana De Torres
B69: Maceo | H69: Panqueba | P69: Paratebueno | AB69: San Andrés
B70: Marinilla | H70: Pauna | P70: Pasca | AB70: San Benito
B71: Montebello | H71: Paya | P71: Puerto Salgar | AB71: San Gil
B72: Murindó | H72: Paz De Río | P72: Pulí | AB72: San Joaquín
B73: Mutatá | H73: Pesca | P73: Quebradanegra | AB73: San José De Miranda
B74: Nariño | H74: Pisba | P74: Quetame | AB74: San Miguel
B75: Necoclí | H75: Puerto Boyacá | P75: Quipile | AB75: San Vicente De Chucurí
B76: Nechí | H76: Quípama | P76: Apulo | AB76: Santa Bárbara
B77: Olaya | H77: Ramiriquí | P77: Ricaurte | AB77: Santa Helena Del Opón
... B88: Sabaneta | H88: San Pablo De Borbur | P88: Soacha | AB88: Zapatoca
B89: Salgar | H89: Santana | P89: Sopó
B90: San Andrés De Cuerquía | H90: Santa María | P90: Subachoque
B91: San Carlos | H91: Santa Rosa De Viterbo | P91: Suesca
B92: San Francisco | H92: Santa Sofía | P92: Supatá
B93: San Jerónimo | H93: Sativanorte | P93: Susa
B94: San José De La Montaña | H94: Sativasur | P94: Sutatausa
B95: San Juan De Urabá | H95: Siachoque | P95: Tabio
B96: San Luis | H96: Soatá | P96: Tausa
B97: San Pedro De Los Milagros | H97: Socotá | P97: Tena
B98: San Pedro De Urabá | H98: Socha | P98: Tenjo
B99: San Rafael | H99: Sogamoso | P99: Tibacuy
B100: San Roque | H100: Somondoco | P100: Tibirita
... B117: Valdivia | H117: Tununguá | P117: Zipaquirá
B118: Valparaíso | H118: Turmequé
B119: Vegachí | H119: Tuta
B120: Venecia | H120: Tutazá
B121: Vigía Del Fuerte | H121: Úmbita
B122: Yalí | H122: Ventaquemada
B123: Yarumal | H123: Viracachá
B124: Yolombó | H124: Zetaquira
B125: Yondó
B126: Zaragoza

Sheet TIPO PN
A2: TIPO_PN
A3: ECONOMÍA_CAMPESINA
A4: MULTISECTORIAL
A8: ECONOMÍA_CAMPESINA | B8: TODOS_LOS_SECTORES
A9: AGROPECUARIO | B9: AGRICULTURA_GANADERÍA_CAZA_SILVICULTURA_Y_PESCA
A10: AGROINDUSTRIA | B10: EXPLOTACIÓN_DE_MINAS_Y_CANTERAS
A11: ARTESANÍAS | B11: INDUSTRIAS_MANUFACTURERAS
A12: TURISMO | B12: SUMINISTRO_DE_ELECTRICIDAD_GAS_VAPOR_Y_AIRE_ACONDICIONADO
A13: MEDIO_AMBIENTE | B13: DISTRIBUCIÓN_DE_AGUA_EVACUACIÓN_Y_TRATAMIENTO_DE_AGUAS_RESIDUALES_GESTIÓN_DE_DESECHOS_Y_ACTIVIDADES_DE_SANEAMIENTO_AMBIENTAL
A14: COMERCIO_EC | B14: CONSTRUCCIÓN
B15: COMERCIO_AL_POR_MAYOR_Y_AL_POR_MENOR_REPARACIÓN_DE_VEHÍCULOS_AUTOMOTORES_Y_MOTOCICLETAS
B16: TRANSPORTE_Y_ALMACENAMIENTO
B17: ALOJAMIENTO_Y_SERVICIOS_DE_COMIDA
B18: INFORMACIÓN_Y_COMUNICACIONES
B19: ACTIVIDADES_FINANCIERAS_Y_DE_SEGUROS
B20: ACTIVIDADES_INMOBILIARIAS
B21: ACTIVIDADES_PROFESIONALES_CIENTÍFICAS_Y_TÉCNICAS
B22: ACTIVIDADES_DE_SERVICIOS_ADMINISTRATIVOS_Y_DE_APOYO
B23: ADMINISTRACIÓN_PÚBLICA_Y_DEFENSA_PLANES_DE_SEGURIDAD_SOCIAL_DE_AFILIACIÓN_OBLIGATORIA
B24: EDUCACIÓN
B25: ACTIVIDADES_DE_ATENCIÓN_DE_LA_SALUD_HUMANA_Y_DE_ASISTENCIA_SOCIAL
B26: ACTIVIDADES_ARTÍSTICAS_DE_ENTRETENIMIENTO_Y_RECREACIÓN
B27: OTRAS_ACTIVIDADES_DE_SERVICIOS

Sheet Sectores EC
A1: AGROPECUARIO | B1: AGROINDUSTRIA | C1: ARTESANÍAS | D1: TURISMO | E1: MEDIO_AMBIENTE | F1: |
A2: 0111 Cultivo de cereales (excepto arroz), legumbres y semillas oleaginosas | B2: 1011 Procesamiento y conservación de carne y productos cárnicos | C2: 1311 Preparación e hilatura de fibras textiles | D2: 5514 Alojamiento rural | E2: 3600 Captación, tratamiento y distribución de agua | F2: 4620 Comercio al por mayor de materias primas agropecuarias; animales vivos
A3: 0112 Cultivo de arroz | B3: 1012 Procesamiento y conservación de pescados, crustáceos y moluscos | C3: 1312 Tejeduría de productos textiles | D3: 5519 Otros tipos de alojamientos para visitantes | E3: 3700 Evacuación y tratamiento de aguas residuales | F3: 463 Comercio al por mayor de alimentos, bebidas y tabaco
A4: 0113 Cultivo de hortalizas, raíces y tubérculos | B4: 1020 Procesamiento y conservación de frutas, legumbres, hortalizas y tubérculos | C4: 1313 Acabado de productos textiles | D4: 5520 Actividades de zonas de camping y parques para vehículos recreacionales | E4: 3811 Recolección de desechos no peligrosos | F4: 4631 Comercio al por mayor de productos alimenticios
A5: 0114 Cultivo de tabaco | B5: 1030 Elaboración de aceites y grasas de origen vegetal y animal | C5: 1391 Fabricación de tejidos de punto y ganchillo | D5: 5590 Otros tipos de alojamiento n.c.p. | E5: 3812 Recolección de desechos peligrosos | F5: 4711 Comercio al por menor en establecimientos no especializados con surtido compuesto principalmente por alimentos, bebidas o tabaco
A6: 0115 Cultivo de plantas textiles | B6: 1040 Elaboración de productos lácteos | C6: 1392 Confección de artículos con materiales textiles, excepto prendas de vestir | D6: 5611 Expendio a la mesa de comidas preparadas | E6: 3821 Tratamiento y disposición de desechos no peligrosos | F6: 4721 Comercio al por menor de productos agrícolas para el consumo en establecimientos especializados
A7: 0119 Otros cultivos transitorios n.c.p. | B7: 1051 Elaboración de productos de molinería | C7: 1393 Fabricación de tapetes y alfombras para pisos | D7: 5612 Expendio por autoservicio de comidas preparadas | E7: 3830 Recuperación de materiales | F7: 4722 Comercio al por menor de leche, productos lácteos y huevos, en establecimientos especializados
A8: 0121 Cultivo de frutas tropicales y subtropicales | B8: 1052 Elaboración de almidones y productos derivados del almidón | C8: 1394 Fabricación de cuerdas, cordeles, cables, bramantes y redes | D8: 5619 Otros tipos de expendio de comidas preparadas n.c.p. | E8: 3900 Actividades de saneamiento ambiental y otros servicios de gestión de desechos | F8: 4723 Comercio al por menor de carnes (incluye aves de corral), productos cárnicos, pescados y productos de mar, en establecimientos especializados
A9: 0122 Cultivo de plátano y banano | B9: 1061 Trilla de café | C9: 1399 Fabricación de otros artículos textiles n.c.p. | D9: 5629 Actividades de otros servicios de comidas
A10: 0123 Cultivo de café | B10: 1062 Descafeinado, tostión y molienda del café | C10: 1410 Confección de prendas de vestir, excepto prendas de piel
A11: 0124 Cultivo de caña de azúcar | B11: 1063 Otros derivados del café | C11: 1420 Fabricación de artículos de piel
A12: 0125 Cultivo de flor de corte | B12: 1071 Elaboración y refinación de azúcar | C12: 1430 Fabricación de artículos de punto y ganchillo
A13: 0126 Cultivo de palma para aceite (palma africana) y otros frutos oleaginosos | B13: 1072 Elaboración de panela | C13: 1511 Curtido y recurtido de cueros; recurtido y teñido de pieles
A14: 0127 Cultivo de plantas con las que se preparan bebidas | B14: 1081 Elaboración de productos de panadería | C14: 1512 Fabricación de artículos de viaje, bolsos de mano y artículos similares elaborados en cuero, y fabricación de artículos de talabartería y guarnicionería
A15: 0128 Cultivo de especias y de plantas aromáticas y medicinales | B15: 1082 Elaboración de cacao, chocolate y productos de confitería | C15: 1513 Fabricación de artículos de viaje, bolsos de mano y artículos similares; artículos de talabartería y guarnicionería elaborados en otros materiales
A16: 0129 Otros cultivos permanentes n.c.p. | B16: 1083 Elaboración de macarrones, fideos, alcuzcuz y productos farináceos similares | C16: 1521 Fabricación de calzado de cuero y piel, con cualquier tipo de suela
A17: 0130 Propagación de plantas (actividades de los viveros, excepto viveros forestales) | B17: 1084 Elaboración de comidas y platos preparados | C17: 1522 Fabricación de otros tipos de calzado, excepto calzado de cuero y piel
A18: 0141 Cría de ganado bovino y bufalino | B18: 1089 Elaboración de otros productos alimenticios n.c.p. | C18: 1523 Fabricación de partes del calzado
A19: 0142 Cría de caballos y otros equinos | B19: 1090 Elaboración de alimentos preparados para animales | C19: 1640 Fabricación de recipientes de madera
A20: 0143 Cría de ovejas y cabras | B20: 1102 Elaboración de bebidas fermentadas no destiladas | C20: 2392 Fabricación de materiales de arcilla para la construcción
A21: 0144 Cría de ganado porcino | B21: 1103 Producción de malta, elaboración de cervezas y otras bebidas malteadas | C21: 2393 Fabricación de otros productos de cerámica y porcelana
A22: 0145 Cría de aves de corral | B22: 1104 Elaboración de bebidas no alcohólicas, producción de aguas minerales y de otras aguas embotelladas | C22: 2396 Corte, tallado y acabado de la piedra
A23: 0149 Cría de otros animales n.c.p.
A24: 0150 Explotación mixta (agrícola y pecuaria)
A25: 0161 Actividades de apoyo a la agricultura
A26: 0162 Actividades de apoyo a la ganadería
A27: 0163 Actividades posteriores a la cosecha
A28: 0164 Tratamiento de semillas para propagación
A29: 0170 Caza ordinaria y mediante trampas y actividades de servicios conexas
A30: 0210 Silvicultura y otras actividades forestales
A31: 0220 Extracción de madera
A32: 0230 Recolección de productos forestales diferentes a la madera
A33: 0240 Servicios de apoyo a la silvicultura
A34: 0311 Pesca marítima
... A37: 0322 Acuicultura de agua dulce

Sheet Sectores EP
A1: AGRICULTURA_GANADERÍA_CAZA_SILVICULTURA_Y_PESCA | B1: EXPLOTACIÓN_DE_MINAS_Y_CANTERAS | C1: INDUSTRIAS_MANUFACTURERAS | D1: SUMINISTRO_DE_ELECTRICIDAD_GAS_VAPOR_Y_AIRE_ACONDICIONADO | E1: DISTRIBUCIÓN_DE_AGUA_EVACUACIÓN_Y_TRATAMIENTO_DE_AGUAS_RESIDUALES_GESTIÓN_DE_DESECHOS_Y_ACTIVIDADES_DE_SANEAMIENTO_AMBIENTAL | F1: CONSTRUCCIÓN | G1: COMERCIO_AL_POR_MAYOR_Y_AL_POR_MENOR_REPARACIÓN_DE_VEHÍCULOS_AUTOMOTORES_Y_MOTOCICLETAS | H1: TRANSPORTE_Y_ALMACENAMIENTO | I1: ALOJAMIENTO_Y_SERVICIOS_DE_COMIDA | J1: INFORMACIÓN_Y_COMUNICACIONES | K1: ACTIVIDADES_FINANCIERAS_Y_DE_SEGUROS | L1: ACTIVIDADES_INMOBILIARIAS | M1: ACTIVIDADES_PROFESIONALES_CIENTÍFICAS_Y_TÉCNICAS | N1: ACTIVIDADES_DE_SERVICIOS_ADMINISTRATIVOS_Y_DE_APOYO | O1: ADMINISTRACIÓN_PÚBLICA_Y_DEFENSA_PLANES_DE_SEGURIDAD_SOCIAL_DE_AFILIACIÓN_OBLIGATORIA | P1: EDUCACIÓN | Q1: ACTIVIDADES_DE_ATENCIÓN_DE_LA_SALUD_HUMANA_Y_DE_ASISTENCIA_SOCIAL | R1: ACTIVIDADES_ARTÍSTICAS_DE_ENTRETENIMIENTO_Y_RECREACIÓN | S1: OTRAS_ACTIVIDADES_DE_SERVICIOS
A2: 0111 Cultivo de cereales (excepto arroz), legumbres y semillas oleaginosas | B2: 0510 Extracción de hulla (carbón de piedra) | C2: 1011 Procesamiento y conservación de carne y productos cárnicos | D2: 3511 Generación de energía eléctrica | E2: 3600 Captación, tratamiento y distribución de agua | F2: 4111 Construcción de edificios residenciales | G2: 4511 Comercio de vehículos automotores nuevos | H2: 4911 Transporte férreo de pasajeros | I2: 5511 Alojamiento en hoteles | J2: 5811 Edición de libros | K2: 6411 Banco Central | L2: 6810 Actividades inmobiliarias realizadas con bienes propios o arrendados | M2: 6910 Actividades jurídicas | N2: 7710 Alquiler y arrendamiento de vehículos automotores | O2: 8411 Actividades legislativas de la administración pública | P2: 8511 Educación de la primera infancia | Q2: 8610 Actividades de hospitales y clínicas, con internación | R2: 9001 Creación literaria | S2: 9411 Actividades de asociaciones empresariales y de empleadores
A3: 0112 Cultivo de arroz | B3: 0520 Extracción de carbón lignito | C3: 1012 Procesamiento y conservación de pescados, crustáceos y moluscos | D3: 3512 Transmisión de energía eléctrica | E3: 3700 Evacuación y tratamiento de aguas residuales | F3: 4112 Construcción de edificios no residenciales | G3: 4512 Comercio de vehículos automotores usados | H3: 4912 Transporte férreo de carga | I3: 5512 Alojamiento en apartahoteles | J3: 5812 Edición de directorios y listas de correo | K3: 6412 Bancos comerciales | L3: 6820 Actividades inmobiliarias realizadas a cambio de una retribución o por contrata | M3: 6920 Actividades de contabilidad, teneduría de libros, auditoría financiera y asesoría tributaria | N3: 7721 Alquiler y arrendamiento de equipo recreativo y deportivo | O3: 8412 Actividades ejecutivas de la administración pública | P3: 8512 Educación preescolar | Q3: 8621 Actividades de la práctica médica, sin internación | R3: 9002 Creación musical | S3: 9412 Actividades de asociaciones profesionales
A4: 0113 Cultivo de hortalizas, raíces y tubérculos | B4: 0610 Extracción de petróleo crudo | C4: 1020 Procesamiento y conservación de frutas, legumbres, hortalizas y tubérculos | D4: 3513 Distribución de energía eléctrica | E4: 3811 Recolección de desechos no peligrosos | F4: 4210 Construcción de carreteras y vías de ferrocarril | G4: 4520 Mantenimiento y reparación de vehículos automotores | H4: 4921 Transporte de pasajeros | I4: 5513 Alojamiento en centros vacacionales | J4: 5813 Edición de periódicos, revistas y otras publicaciones periódicas | K4: 6421 Actividades de las corporaciones financieras | M4: 7010 Actividades de administración empresarial | N4: 7722 Alquiler de videos y discos | O4: 8413 Regulación de las actividades de organismos que prestan servicios de salud, educativos, culturales y otros servicios sociales, excepto servicios de seguridad social | P4: 8513 Educación básica primaria | Q4: 8622 Actividades de la práctica odontológica | R4: 9003 Creación teatral | S4: 9420 Actividades de sindicatos de empleados
A5: 0114 Cultivo de tabaco | B5: 0620 Extracción de gas natural | C5: 1030 Elaboración de aceites y grasas de origen vegetal y animal | D5: 3514 Comercialización de energía eléctrica | E5: 3812 Recolección de desechos peligrosos | F5: 4220 Construcción de proyectos de servicio público | G5: 4530 Comercio de partes, piezas (autopartes) y accesorios (lujos) para vehículos automotores | H5: 4922 Transporte mixto | I5: 5514 Alojamiento rural | J5: 5819 Otros trabajos de edición | K5: 6422 Actividades de las compañías de financiamiento | M5: 7020 Actividades de consultaría de gestión | N5: 7729 Alquiler y arrendamiento de otros efectos personales y enseres domésticos n.c.p. | O5: 8414 Actividades reguladoras y facilitadoras de la actividad económica | P5: 8521 Educación básica secundaria | Q5: 8691 Actividades de apoyo diagnóstico | R5: 9004 Creación audiovisual | S5: 9491 Actividades de asociaciones religiosas
A6: 0115 Cultivo de plantas textiles | B6: 0710 Extracción de minerales de hierro | C6: 1040 Elaboración de productos lácteos | D6: 3520 Producción de gas; distribución de combustibles gaseosos por tuberías | E6: 3821 Tratamiento y disposición de desechos no peligrosos | F6: 4290 Construcción de otras obras de ingeniería civil | G6: 4541 Comercio de motocicletas y de sus partes, piezas y accesorios | H6: 4923 Transporte de carga por carretera | I6: 5519 Otros tipos de alojamientos para visitantes | J6: 5820 Edición de programas de informática (software) | K6: 6423 Banca de segundo piso | M6: 7110 Actividades de arquitectura e ingeniería y otras actividades conexas de consultoría técnica | N6: 7730 Alquiler y arrendamiento de otros tipos de maquinaria, equipo y bienes tangibles n.c.p. | O6: 8415 Actividades de los otros órganos de control | P6: 8522 Educación media académica | Q6: 8692 Actividades de apoyo terapéutico | R6: 9005 Artes plásticas y visuales | S6: 9492 Actividades de asociaciones políticas
A7: 0119 Otros cultivos transitorios n.c.p. | B7: 0721 Extracción de minerales de uranio y de torio | C7: 1051 Elaboración de productos de molinería | D7: 3530 Suministro de vapor y aire acondicionado | E7: 3822 Tratamiento y disposición de desechos peligrosos | F7: 4311 Demolición | G7: 4542 Mantenimiento y reparación de motocicletas y de sus partes y piezas | H7: 4930 Transporte por tuberías | I7: 5520 Actividades de zonas de camping y parques para vehículos recreacionales | J7: 5911 Actividades de producción de películas cinematográficas, videos, programas, anuncios y comerciales de televisión | K7: 6424 Actividades de las cooperativas financieras | M7: 7120 Ensayos y análisis técnicos | N7: 7740 Arrendamiento de propiedad intelectual y productos similares, excepto obras protegidas por derechos de autor | O7: 8421 Relaciones exteriores | P7: 8523 Educación media técnica y de formación laboral | Q7: 8699 Otras actividades de atención de la salud humana | R7: 9006 Actividades teatrales | S7: 9499 Actividades de otras asociaciones n.c.p.
A8: 0121 Cultivo de frutas tropicales y subtropicales | B8: 0722 Extracción de oro y otros metales preciosos | C8: 1052 Elaboración de almidones y productos derivados del almidón | E8: 3830 Recuperación de materiales | F8: 4312 Preparación del terreno | G8: 4610 Comercio al por mayor a cambio de una retribución o por contrata4610 | H8: 5011 Transporte de pasajeros marítimo y de cabotaje | I8: 5530 Servicio por horas | J8: 5912 Actividades de posproducción de películas cinematográficas, videos, programas, anuncios y comerciales de televisión | K8: 6431 Fideicomisos, fondos y entidades financieras similares | M8: 7210 Investigaciones y desarrollo experimental en el campo de las ciencias naturales y la ingeniería | N8: 7810 Actividades de agencias de empleo | O8: 8422 Actividades de defensa | P8: 8530 Establecimientos que combinan diferentes niveles de educación | Q8: 8710 Actividades de atención residencial medicalizada de tipo general | R8: 9007 Actividades de espectáculos musicales en vivo | S8: 9511 Mantenimiento y reparación de computadores y de equipo periférico
A9: 0122 Cultivo de plátano y banano | B9: 0723 Extracción de minerales de níquel | C9: 1061 Trilla de café | E9: 3900 Actividades de saneamiento ambiental y otros servicios de gestión de desechos | F9: 4321 Instalaciones eléctricas | G9: 4620 Comercio al por mayor de materias primas agropecuarias; animales vivos | H9: 5012 Transporte de carga marítimo y de cabotaje | I9: 5590 Otros tipos de alojamiento n.c.p. | J9: 5913 Actividades de distribución de películas cinematográficas, videos, programas, anuncios y comerciales de televisión | K9: 6432 Fondos de cesantías | M9: 7220 Investigaciones y desarrollo experimental en el campo de las ciencias sociales y las humanidades | N9: 7820 Actividades de agencias de empleo temporal | O9: 8423 Orden público y actividades de seguridad | P9: 8541 Educación técnica profesional | Q9: 8720 Actividades de atención residencial, para el cuidado de pacientes con retardo mental, enfermedad mental y consumo de sustancias psicoactivas | R9: 9008 Otras actividades de espectáculos en vivo | S9: 9512 Mantenimiento y reparación de equipos de comunicación
A10: 0123 Cultivo de café | B10: 0724 Extracción de otros minerales metalíferos no ferrosos n.c.p. | C10: 1062 Descafeinado, tostión y molienda del café | F10: 4322 Instalaciones de fontanería, calefacción y aire acondicionado | G10: 4631 Comercio al por mayor de productos alimenticios | H10: 5021 Transporte fluvial de pasajeros | I10: 5611 Expendio a la mesa de comidas preparadas | J10: 5914 Actividades de exhibición de películas cinematográficas y videos | K10: 6491 Leasing financiero (arrendamiento financiero) | M10: 7310 Publicidad | N10: 7830 Otras actividades de suministro de recurso humano | O10: 8424 Administración de justicia | P10: 8542 Educación tecnológica | Q10: 8730 Actividades de atención en instituciones para el cuidado de personas mayores y/o discapacitadas | R10: 9101 Actividades de bibliotecas y archivos | S10: 9521 Mantenimiento y reparación de aparatos electrónicos de consumo
A11: 0124 Cultivo de caña de azúcar | B11: 0811 Extracción de piedra, arena, arcillas comunes, yeso y anhidrita | C11: 1063 Otros derivados del café | F11: 4329 Otras instalaciones especializadas | G11: 4632 Comercio al por mayor de bebidas y tabaco | H11: 5022 Transporte fluvial de carga | I11: 5612 Expendio por autoservicio de comidas preparadas | J11: 5920 Actividades de grabación de sonido y edición de música | K11: 6492 Actividades financieras de fondos de empleados y otras formas asociativas del sector solidario | M11: 7320 Estudios de mercado y realización de encuestas de opinión pública | N11: 7911 Actividades de las agencias de viaje | O11: 8430 Actividades de planes de seguridad social de afiliación obligatoria | P11: 8543 Educación de instituciones universitarias o de escuelas tecnológicas | Q11: 8790 Otras actividades de atención en instituciones con alojamiento | R11: 9102 Actividades y funcionamiento de museos, conservación de edificios y sitios históricos | S11: 9522 Mantenimiento y reparación de aparatos y equipos domésticos y de jardinería
A12: 0125 Cultivo de flor de corte | B12: 0812 Extracción de arcillas de uso industrial, caliza, caolín y bentonitas | C12: 1071 Elaboración y refinación de azúcar | F12: 4330 Terminación y acabado de edificios y obras de ingeniería civil | G12: 4641 Comercio al por mayor de productos textiles, productos confeccionados para uso doméstico | H12: 5111 Transporte aéreo nacional de pasajeros | I12: 5613 Expendio de comidas preparadas en cafeterías | J12: 6010 Actividades de programación y transmisión en el servicio de radiodifusión sonora | K12: 6493 Actividades de compra de cartera o factoring | M12: 7410 Actividades especializadas de diseño | N12: 7912 Actividades de operadores turísticos | P12: 8544 Educación de universidades | Q12: 8810 Actividades de asistencia social sin alojamiento para personas mayores y discapacitadas | R12: 9103 Actividades de jardines botánicos, zoológicos y reservas naturales | S12: 9523 Reparación de calzado y artículos de cuero
A13: 0126 Cultivo de palma para aceite (palma africana) y otros frutos oleaginosos | B13: 0820 Extracción de esmeraldas, piedras preciosas y semipreciosas | C13: 1072 Elaboración de panela | F13: 4390 Otras actividades especializadas para la construcción de edificios y obras de ingeniería civil | G13: 4642 Comercio al por mayor de prendas de vestir | H13: 5112 Transporte aéreo internacional de pasajeros | I13: 5619 Otros tipos de expendio de comidas preparadas n.c.p. | J13: 6020 Actividades de programación y transmisión de televisión | K13: 6494 Otras actividades de distribución de fondos | M13: 7420 Actividades de fotografía | N13: 7990 Otros servicios de reserva y actividades relacionadas | P13: 8551 Formación académica no formal | Q13: 8890 Otras actividades de asistencia social sin alojamiento | R13: 9200 Actividades de juegos de azar y apuestas | S13: 9524 Reparación de muebles y accesorios para el hogar
A14: 0127 Cultivo de plantas con las que se preparan bebidas | B14: 0891 Extracción de minerales para la fabricación de abonos y productos químicos | C14: 1081 Elaboración de productos de panadería | G14: 4643 Comercio al por mayor de calzado | H14: 5121 Transporte aéreo nacional de carga | I14: 5621 Catering para eventos | J14: 6110 Actividades de telecomunicaciones alámbricas | K14: 6495 Instituciones especiales oficiales | M14: 7490 Otras actividades profesionales, científicas y técnicas n.c.p. | N14: 8010 Actividades de seguridad privada | P14: 8552 Enseñanza deportiva y recreativa | R14: 9311 Gestión de instalaciones deportivas | S14: 9529 Mantenimiento y reparación de otros efectos personales y enseres domésticos
A15: 0128 Cultivo de especias y de plantas aromáticas y medicinales | B15: 0892 Extracción de halita (sal) | C15: 1082 Elaboración de cacao, chocolate y productos de confitería | G15: 4644 Comercio al por mayor de aparatos y equipo de uso doméstico | H15: 5122 Transporte aéreo internacional de carga | I15: 5629 Actividades de otros servicios de comidas | J15: 6120 Actividades de telecomunicaciones inalámbricas | K15: 6499 Otras actividades de servicio financiero, excepto las de seguros y pensiones n.c.p. | M15: 7500 Actividades veterinarias | N15: 8020 Actividades de servicios de sistemas de seguridad | P15: 8553 Enseñanza cultural | R15: 9312 Actividades de clubes deportivos | S15: 9601 Lavado y limpieza, incluso la limpieza en seco, de productos textiles y de piel
A16: 0129 Otros cultivos permanentes n.c.p. | B16: 0899 Extracción de otros minerales no metálicos n.c.p. | C16: 1083 Elaboración de macarrones, fideos, alcuzcuz y productos farináceos similares | G16: 4645 Comercio al por mayor de productos farmacéuticos, medicinales, cosméticos y de tocador | H16: 5210 Almacenamiento y depósito | I16: 5630 Expendio de bebidas alcohólicas para el consumo dentro del establecimiento | J16: 6130 Actividades de telecomunicación satelital | K16: 6511 Seguros generales | N16: 8030 Actividades de detectives e investigadores privados | P16: 8559 Otros tipos de educación n.c.p. | R16: 9319 Otras actividades deportivas | S16: 9602 Peluquería y otros tratamientos de belleza
A17: 0130 Propagación de plantas (actividades de los viveros, excepto viveros forestales) | B17: 0910 Actividades de apoyo para la extracción de petróleo y de gas natural | C17: 1084 Elaboración de comidas y platos preparados | G17: 4649 Comercio al por mayor de otros utensilios domésticos n.c.p. | H17: 5221 Actividades de estaciones, vías y servicios complementarios para el transporte terrestre | J17: 6190 Otras actividades de telecomunicaciones | K17: 6512 Seguros de vida | N17: 8110 Actividades combinadas de apoyo a instalaciones | P17: 8560 Actividades de apoyo a la educación | R17: 9321 Actividades de parques de atracciones y parques temáticos | S17: 9603 Pompas fúnebres y actividades relacionadas
A18: 0141 Cría de ganado bovino y bufalino | B18: 0990 Actividades de apoyo para otras actividades de explotación de minas y canteras | C18: 1089 Elaboración de otros productos alimenticios n.c.p. | G18: 4651 Comercio al por mayor de computadores, equipo periférico y programas de informática | H18: 5222 Actividades de puertos y servicios complementarios para el transporte acuático | J18: 6201 Actividades de desarrollo de sistemas informáticos (planificación, análisis, diseño, programación, pruebas) | K18: 6513 Reaseguros | N18: 8121 Limpieza general interior de edificios | R18: 9329 Otras actividades recreativas y de esparcimiento n.c.p. | S18: 9609 Otras actividades de servicios personales n.c.p.
A19: 0142 Cría de caballos y otros equinos | C19: 1090 Elaboración de alimentos preparados para animales | G19: 4652 Comercio al por mayor de equipo, partes y piezas electrónicos y de telecomunicaciones | H19: 5223 Actividades de aeropuertos, servicios de navegación aérea y demás actividades conexas al transporte aéreo | J19: 6202 Actividades de consultoría informática y actividades de administración de instalaciones informáticas | K19: 6514 Capitalización | N19: 8129 Otras actividades de limpieza de edificios e instalaciones industriales | S19: 9909 Actividades de organizaciones y entidades extraterritoriales
A20: 0143 Cría de ovejas y cabras | C20: 1101 Destilación, rectificación y mezcla de bebidas alcohólicas | G20: 4653 Comercio al por mayor de maquinaria y equipo agropecuarios | H20: 5224 Manipulación de carga | J20: 6209 Otras actividades de tecnologías de información y actividades de servicios informáticos | K20: 6521 Servicios de seguros sociales de salud | N20: 8130 Actividades de paisajismo y servicios de mantenimiento conexos
A21: 0144 Cría de ganado porcino | C21: 1102 Elaboración de bebidas fermentadas no destiladas | G21: 4659 Comercio al por mayor de otros tipos de maquinaria y equipo n.c.p. | H21: 5229 Otras actividades complementarias al transporte | J21: 6311 Procesamiento de datos, alojamiento (hosting) y actividades relacionadas | K21: 6522 Servicios de seguros sociales de riesgos profesionales | N21: 8211 Actividades combinadas de servicios administrativos de oficina
A22: 0145 Cría de aves de corral | C22: 1103 Producción de malta, elaboración de cervezas y otras bebidas malteadas | G22: 4661 Comercio al por mayor de combustibles sólidos, líquidos, gaseosos y productos conexos | H22: 5310 Actividades postales nacionales | J22: 6312 Portales web | K22: 6531 Régimen de prima media con prestación definida (RPM) | N22: 8219 Fotocopiado, preparación de documentos y otras actividades especializadas de apoyo a oficina
A23: 0149 Cría de otros animales n.c.p. | C23: 1104 Elaboración de bebidas no alcohólicas, producción de aguas minerales y de otras aguas embotelladas | G23: 4662 Comercio al por mayor de metales y productos metalíferos | H23: 5320 Actividades de mensajería | J23: 6391 Actividades de agencias de noticias | K23: 6532 Régimen de ahorro individual (RAI) | N23: 8220 Actividades de centros de llamadas (Call center)
A24: 0150 Explotación mixta (agrícola y pecuaria) | C24: 1200 Elaboración de productos de tabaco | G24: 4663 Comercio al por mayor de materiales de construcción, artículos de ferretería, pinturas, productos de vidrio, equipo y materiales de fontanería y calefacción | J24: 6399 Otras actividades de servicio de información n.c.p. | K24: 6611 Administración de mercados financieros | N24: 8230 Organización de convenciones y eventos comerciales
A25: 0161 Actividades de apoyo a la agricultura | C25: 1311 Preparación e hilatura de fibras textiles | G25: 4664 Comercio al por mayor de productos químicos básicos, cauchos y plásticos en formas primarias y productos químicos de uso agropecuario | K25: 6612 Corretaje de valores y de contratos de productos básicos | N25: 8291 Actividades de agencias de cobranza y oficinas de calificación crediticia
A26: 0162 Actividades de apoyo a la ganadería | C26: 1312 Tejeduría de productos textiles | G26: 4665 Comercio al por mayor de desperdicios, desechos y chatarra | K26: 6613 Otras actividades relacionadas con el mercado de valores | N26: 8292 Actividades de envase y empaque
A27: 0163 Actividades posteriores a la cosecha | C27: 1313 Acabado de productos textiles | G27: 4669 Comercio al por mayor de otros productos n.c.p. | K27: 6614 Actividades de las casas de cambio | N27: 8299 Otras actividades de servicio de apoyo a las empresas n.c.p.
A28: 0164 Tratamiento de semillas para propagación | C28: 1391 Fabricación de tejidos de punto y ganchillo | G28: 4690 Comercio al por mayor no especializado | K28: 6615 Actividades de los profesionales de compra y venta de divisas
A29: 0170 Caza ordinaria y mediante trampas y actividades de servicios conexas | C29: 1392 Confección de artículos con materiales textiles, excepto prendas de vestir | G29: 4711 Comercio al por menor en establecimientos no especializados con surtido compuesto principalmente por alimentos, bebidas o tabaco | K29: 6619 Otras actividades auxiliares de las actividades de servicios financieros n.c.p.
A30: 0210 Silvicultura y otras actividades forestales | C30: 1393 Fabricación de tapetes y alfombras para pisos | G30: 4719 Comercio al por menor en establecimientos no especializados, con surtido compuesto principalmente por productos diferentes de alimentos (víveres en general), bebidas y tabaco | K30: 6621 Actividades de agentes y corredores de seguros
A31: 0220 Extracción de madera | C31: 1394 Fabricación de cuerdas, cordeles, cables, bramantes y redes | G31: 4721 Comercio al por menor de productos agrícolas para el consumo en establecimientos especializados | K31: 6629 Evaluación de riesgos y daños, y otras actividades de servicios auxiliares
A32: 0230 Recolección de productos forestales diferentes a la madera | C32: 1399 Fabricación de otros artículos textiles n.c.p. | G32: 4722 Comercio al por menor de leche, productos lácteos y huevos, en establecimientos especializados | K32: 6630 Actividades de administración de fondos
A33: 0240 Servicios de apoyo a la silvicultura | C33: 1410 Confección de prendas de vestir, excepto prendas de piel | G33: 4723 Comercio al por menor de carnes (incluye aves de corral), productos cárnicos, pescados y productos de mar, en establecimientos especializados
A34: 0311 Pesca marítima | C34: 1420 Fabricación de artículos de piel | G34: 4724 Comercio al por menor de bebidas y productos del tabaco, en establecimientos especializados
A35: 0312 Pesca de agua dulce | C35: 1430 Fabricación de artículos de punto y ganchillo | G35: 4729 Comercio al por menor de otros productos alimenticios n.c.p., en establecimientos especializados
A36: 0321 Acuicultura marítima | C36: 1511 Curtido y recurtido de cueros; recurtido y teñido de pieles | G36: 4731 Comercio al por menor de combustible, lubricantes, aditivos y productos de limpieza para automotores, en establecimientos especializados
A37: 0322 Acuicultura de agua dulce | C37: 1512 Fabricación de artículos de viaje, bolsos de mano y artículos similares elaborados en cuero, y fabricación de artículos de talabartería y guarnicionería | G37: 4732 Comercio al por menor de combustible para automotores
C38: 1513 Fabricación de artículos de viaje, bolsos de mano y artículos similares; artículos de talabartería y guarnicionería elaborados en otros materiales | G38: 4741 Comercio al por menor de lubricantes (aceites, grasas), aditivos y productos de limpieza para vehículos automotores
C39: 1521 Fabricación de calzado de cuero y piel, con cualquier tipo de suela | G39: 4742 Comercio al por menor de equipos y aparatos de sonido y de video, en establecimientos especializados
C40: 1522 Fabricación de otros tipos de calzado, excepto calzado de cuero y piel | G40: 4751 Comercio al por menor de productos textiles en establecimientos especializados
C41: 1523 Fabricación de partes del calzado | G41: 4752 Comercio al por menor de artículos de ferretería, pinturas y productos de vidrio en establecimientos especializados
C42: 1610 Aserrado, acepillado e impregnación de la madera | G42: 4753 Comercio al por menor de tapices, alfombras y cubrimientos para paredes y pisos en establecimientos especializados
C43: 1620 Fabricación de hojas de madera para enchapado; fabricación de tableros contrachapados, tableros laminados, tableros de partículas y otros tableros y paneles | G43: 4754 Comercio al por menor de electrodomésticos y gasodomésticos de uso doméstico, muebles y equipos de iluminación
C44: 1630 Fabricación de partes y piezas de madera, de carpintería y ebanistería para la construcción | G44: 4755 Comercio al por menor de artículos y utensilios de uso doméstico
C45: 1640 Fabricación de recipientes de madera | G45: 4759 Comercio al por menor de otros artículos domésticos en establecimientos especializados
C46: 1690 Fabricación de otros productos de madera; fabricación de artículos de corcho, cestería y espartería | G46: 4761 Comercio al por menor de libros, periódicos, materiales y artículos de papelería y escritorio, en establecimientos especializados
C47: 1701 Fabricación de pulpas (pastas) celulósicas; papel y cartón | G47: 4762 Comercio al por menor de artículos deportivos, en establecimientos especializados
C48: 1702 Fabricación de papel y cartón ondulado (corrugado); fabricación de envases, empaques y de embalajes de papel y cartón. | G48: 4769 Comercio al por menor de otros artículos culturales y de entretenimiento n.c.p. en establecimientos especializados
C49: 1709 Fabricación de otros artículos de papel y cartón | G49: 4771 Comercio al por menor de prendas de vestir y sus accesorios (incluye artículos de piel) en establecimientos especializados
... C59: 2014 Fabricación de caucho sintético en formas primarias | G59: 4799 Otros tipos de comercio al por menor no realizado en establecimientos, puestos de venta o mercados.
C60: 2021 Fabricación de plaguicidas y otros productos químicos de uso agropecuario
C61: 2022 Fabricación de pinturas, barnices y revestimientos similares, tintas para impresión y masillas
C62: 2023 Fabricación de jabones y detergentes, preparados para limpiar y pulir; perfumes y preparados de tocador
C63: 2029 Fabricación de otros productos químicos n.c.p.
C64: 2030 Fabricación de fibras sintéticas y artificiales
C65: 2100 Fabricación de productos farmacéuticos, sustancias químicas medicinales y productos botánicos de uso farmacéutico
C66: 2211 Fabricación de llantas y neumáticos de caucho
C67: 2212 Reencauche de llantas usadas
C68: 2219 Fabricación de formas básicas de caucho y otros productos de caucho n.c.p.
C69: 2221 Fabricación de formas básicas de plástico
C70: 2229 Fabricación de artículos de plástico n.c.p.
C71: 2310 Fabricación de vidrio y productos de vidrio
... C150: 3320 Instalación especializada de maquinaria y equipo industrial

Sheet Instrucciones
A4: Coordinación Nacional de Emprendimiento, Dirección de Empleo y Trabajo (2026)
A6: INSTRUCCIONES
A7: Este instrumento orienta el registro de la información necesaria para estructurar el plan de negocio de una iniciativa productiva para CREAR. DILIGENCIE ÚNICAMENTE LAS CELDAS SOMBREADAS EN GRIS. Se debe mantener la estructura original de la herramienta, sin realizar cambios en las columnas, pestañas, fórmulas, formatos de celdas o cualquier otro elemento que afecte su integridad. La información debe diligenciarse de manera clara, coherente y verificable, considerando que esta es la herramienta para el análisis técnico, comercial, financiero y jurídico del proyecto en la fase de EVALUACIÓN. Durante la Ruta Emprendedora, el SENA acompaña el proceso de formulación; sin embargo, la información registrada es responsabilidad del emprendedor o grupo postulante.
A8: HOJA 1 PROYECTO
A9: INFORMACIÓN DEL PROYECTO
A10: Permite identificar las características generales de la iniciativa. Líder o representante de la iniciativa: Registre los nombres y apellidos completos de la persona líder o representante del proyecto, Nombre de la iniciativa: Ingrese el nombre con el cual se identificará el negocio. Debe ser claro y coherente con la actividad económica. Categoría del sector económico: Seleccione la categoría correspondiente según la caracterización del emprendedor o grupo, conforme a las condiciones de la convocatoria. Si elige la categoría CAMPESINOS desplegará únicamente los sectores y las actividades permitidas para la Economía Campesina de acuerdo a los indicado en los términos de referencia de cada convocatoria Si elige la categoría TODOS LOS SECTORES desplegará todos los sectores y actividades económicas vigentes, las cuales también aplican para Economía Popular. La elección de la categoría dependerá del autorreconocimiento o caracterización del representante o grupo asociativo y de la focalización que disponga la Convocatoria a la que desee postularse. Tipo de proyecto: Seleccione la opción que describa el tipo de iniciativa que se pretende desarrollar. En caso de ser asociativo, indicar cuántas personas hacen parte del grupo asociativo, las cuales deben coincidir en todo el proyecto y en los documentos de acreditación para su postulación. Lugar de operación: Indique si cuenta con un lugar donde funcionará la iniciativa. El lugar de operación corresponde al sitio donde se desarrollarán las actividades productivas o comerciales. En caso de resultar beneficiario de recursos, deberá evidenciarse la gestión del lugar de operación mediante documentos como: certificado de uso del suelo, certificado de tradición y libertad o certificación de sana posesión, según aplique, dentro del plazo establecido en el proceso contractual.
A11: 1.¿QUIEN ES EL CLIENTE DE SU INICIATIVA? (Quien compra mis productos o servicios)
A12: En este espacio debe identificar claramente a su cliente, es decir, la persona o grupo que le va a comprar los productos o servicios. Escríbalo con el mayor detalle posible: quién es, cómo vive, qué edad tiene, qué gustos o necesidades tiene y por qué le compraría. La idea es que lo describa como si estuviera hablando de un hijo o de un familiar muy cercano, conociendo sus costumbres, lo que le gusta y lo que necesita. Describa las características del cliente o consumidor (los cuales pueden ser diferentes) que comprará su producto o servicio. Indique dónde vive (región, sector (sector urbano, rural), vereda, municipio o ciudad), su estrato socieconómico, rango de edad y género. Explique su capacidad de compra o nivel de ingresos, es decir, si tiene los ingresos suficientes y la frecuencia para poder pagar por el producto o servicio. Señale si trabaja y en qué, su estado civil, la estructura familar, si tiene hijos y si vive en casa propia o en arriendo. También describa sus hábitos de consumo, como cada cuánto compra, qué cantidad consume y qué prefiere al momento de elegir. Incluya cifras o estadísticas que ayuden a mostrar mejor este perfil. Indique el tamaño del mercado desde lo general a lo particular con los criterios que se consideraron para su determinación. Debe describir con detalle cómo es su cliente en cuanto a gustos y preferencias. Mencione qué cosas le gustan, qué le da miedo, qué lo hace feliz y cuáles es su estilo de vida, actividades que realiza, intereses, opiniones, personalidad, ventajas deseadas del producto, usos que da al producto, ocasiones en que lo compra, frecuencia de compra, cantidad de compra, medios de pago (efectivo, transferencia, crédito), valores y creencias. También puede contar qué le gusta comer, si disfruta viajar u otras actividades que hagan parte de su vida. La idea es conocer al cliente como a un familiar cercano, entendiendo sus costumbres, motivaciones y forma de vivir, para saber mejor cómo ofrecerle el producto o servicio.
A13: 2. PLANTEAMIENTO DEL PROBLEMA O NECESIDAD QUE SE PRETENDE SOLUCIONAR
A14: En este espacio identifique el dolor o la necesidad no resuelta del cliente o consumidor que solucionará al usar el producto o servicio. Este elemento busca que se responde a la pregunta ¿Cuál es el problema o necesidad que se pretende solucionar? ¿Cómo le estoy ayudando al cliente? Ojo! No es su problema personal o del grupo asociativo, sino el problema o necesidad del posible cliente del punto anterior.
A15: 3. LA COMPETENCIA (Quien más lo hace?)
A16: Siempre hay competencia, hay que reconocerlo y son esos que hacen lo mismo que queremos hacer, o los que con su producto o servicio reemplazan lo que queremos hacer, describa tres (3) competidores y en qué se diferencia de ellos. Identifique los principales competidores que ofrecen productos o servicios similares. Describa sus características generales y los aspectos que los clientes valoran de ellos. Explique qué hace diferente su iniciativa frente a la competencia y por qué los clientes preferirían adquirir su producto o servicio. Puede relacionarse con calidad, precio, ubicación, innovación, servicio al cliente, experiencia u otros factores diferenciadores.
... A55: Esta hoja no debe ser diligenciada por el emprendedor o grupo asociativo

Sheet Proyecto
B6: Coordinación Nacional de Emprendimiento, Dirección de Empleo y Trabajo (2026)
B8: ID del proyecto
B9: Convocatoria a la que postula la iniciativa
B10: Fecha de diligenciamiento
B12: INICIATIVA PRODUCTIVA, UNIDAD PRODUCTIVA, UNIDAD ECONÓMICA, MODELO O PLAN DE NEGOCIO A CREAR | BM12: SI | BN12: CC | BO12: Aporte Emprendedor
BM13: NO | BN13: CE | BO13: Fondo Emprender
B14: NOMBRES Y APELLIDOS DEL LÍDER O REPRESENTANTE DE LA INICIATIVA | T14: TIPO DE DOCUMENTO | AC14: NÚMERO
B15: Mariano García Posada | T15: CC | AC15: 8026979
BM16: Femenino | BQ16: Adolescentes en Conflicto con la Ley Penal
BM17: Masculino | BQ17: Adolescente Trabajador
B18: NOMBRE DE LA INICIATIVA | T18: DEPARTAMENTO | AC18: MUNICIPIO | BM18: Otro | BQ18: Adolescentes y Jóvenes Vulnerables
B19: AI4U | T19: Antioquia | AC19: Rionegro | BQ19: Afrocolombianos
BM20: Gestión y Administración | BQ20: Campesino
BM21: Transparencia y Responsabilidad: | BQ21: Desplazado por fenómenos naturales
B22: Si elige la categoría CAMPESINOS desplegará únicamente los sectores y las actividades permitidas para la Economía Campesina de acuerdo a los indicado en los términos de referencia de cada convocatoria Si elige la categoría TODOS LOS SECTORES desplegará todos los sectores y actividades económicas vigentes, las cuales también aplican para Economía Popular. La elección de la categoría dependerá del autorreconocimiento o caracterización del representante o grupo asociativo y de la focalización que disponga la Convocatoria a la que desee postularse.
B24: CATEGORÍA DEL SECTOR ECONÓMICO DE LA INICIATIVA | L24: SECTOR (Previamente seleccione la categoría) | Z24: ACTIVIDAD ECONÓMICA (Previamente seleccione el sector)
B25: TODOS_LOS_SECTORES | L25: INFORMACIÓN_Y_COMUNICACIONES | Z25: 6209 Otras actividades de tecnologías de información y actividades de servicios informáticos
B28: Tipo de proyecto | M28: Individual | U28: Registrar en la hoja "Integrantes iniciativa" el total de integrantes, los cuales se verán reflejados acá una vez se hayan diligenciado | AN28: =+'Integrantes Iniciativa'!F14 -> 1 | AV28: SI | BQ28: Palenqueros
AV29: NO | BM29: Contrato Laboral a término fijo | BQ29: Participanes del programa de reintegración - Reintegrados (ARN)
B30: ¿Cuenta con un lugar de operaciones? | R30: SI | BM30: Contrato Laboral a término indefinido | BQ30: Personas en Proceso de Reincorporación
BM31: Prestación de servicios | BQ31: Población LGBTI
A32: Para desarrollar su iniciativa productiva, unidad productiva, unidad económica, modelo o plan de negocio debe contar con un lugar de operaciones. Si llega a ser beneficiario de los recursos del Fondo Emprender, en el momento de la firma del Acta de inicio, se debe evidenciar la gestión del sitio de operaciones; para este caso, se solicita que, se presente uso de suelos donde se tiene planeado realizar la actividad económica y el certificado de tradición donde se demuestre la sana posesión del inmueble o certificación de la sana posesión(Alcaldía). Si el predio está en sucesión se recomienda haber iniciado el proceso o iniciarlo y que se cuente con la autorización de todos los involucrados. El plazo máximo será no mayor a un mes de la suscripción del acta de inicio del contrato de cooperación empresarial para estos documentos. En caso de superar este plazo, el contrato de cooperación empresarial se terminará unilateralmente, por lo que es fundamental prever el lugar de operaciones de su iniciativa productiva, unidad productiva, unidad económica, modelo o plan de negocio desde este momento, la formulación. | BM32: Contrato por obra o Labor | BQ32: Población con discapacidad
A33: Al tomar la decisión de desarrollar una iniciativa productiva, unidad productiva, unidad económica, modelo o plan de negocio es importante tener clara la información de ¿Qué queremos hacer? ¿Cómo lo vamos a hacer? ¿Que vamos a vender? ¿Quien nos va a comprar? entre otros. Con el acompañamiento del SENA, vamos a orientarlo para que construya su iniciativa productiva. | BM33: Jornal | BQ33: Población indígena
BQ34: Población víctima de minas antipersona
BM35: 1 | BQ35: Pueblo ROM
BM36: 2 | BQ36: Raizales
BM37: 3 | BQ37: Remitidos por programa de adaptación laboral - PAL
BM38: 4 | BQ38: Soldados campesinos
BM39: 5 | BQ39: Tercera edad
BM40: 6 | BQ40: Veteranos
BM41: 7 | BQ41: Víctima de otros hechos victimizantes
BM42: 8 | BQ42: Víctima de violencia
BM43: 9 | BQ43: Víctimas Sobrevivientes con Agentes Químicos
BM44: 10
BM45: 11
BM46: 12
A54: INSTRUCCIONES GENERALES:
A55: Para el diligenciamiento de esta herramienta, se debe tener el acompañamiento del Centro de Desarrollo Empresarial del SENA más cercano, donde el equipo de profesionales organizarán su participación en una serie de talleres que les guiarán en la construcción del proyecto y el diligenciamiento de esta herramienta. Diligenciar solamente las celdas sombreadas en gris. Se solicita mantener la estructura original de la herramienta, sin realizar cambios en las columnas, pestañas, fórmulas, formatos de celdas o cualquier otro elemento que afecte su integridad.
A59: 1.¿QUIEN ES EL CLIENTE DE SU INICIATIVA? (Quien compra mis productos o servicios)
A61: En este espacio debe identificar claramente a su cliente, es decir, la persona o grupo que le va a comprar los productos o servicios. Escríbalo con el mayor detalle posible: quién es, cómo vive, qué edad tiene, qué gustos o necesidades tiene y por qué le compraría. La idea es que lo describa como si estuviera hablando de un hijo o de un familiar muy cercano, conociendo sus costumbres, lo que le gusta y lo que necesita.
A64: CARACTERÍSTICAS DEL CLIENTE O CONSUMIDOR En este espacio describa las características del cliente o consumidor que comprará su producto o servicio. Indique dónde vive (región, sector (sector urbano, rural), vereda, municipio o ciudad), su estrato socieconómico, rango de edad y género. Explique su capacidad de compra o nivel de ingresos, es decir, si tiene los ingresos suficientes y la frecuencia para poder pagar por el producto o servicio. Señale si trabaja y en qué, su estado civil, la estructura familar, si tiene hijos y si vive en casa propia o en arriendo. También describa sus hábitos de consumo, como cada cuánto compra, qué cantidad consume y qué prefiere al momento de elegir. Incluya cifras o estadísticas que ayuden a mostrar mejor este perfil. Indique el tamaño del mercado desde lo general a lo particular con los criterios que se consideraron para su determinación. | S64: CUALIDADES DEL CLIENTE O CONSUMIDOR En este espacio debe describir con detalle cómo es su cliente en cuanto a gustos y preferencias. Mencione qué cosas le gustan, qué le da miedo, qué lo hace feliz y cuáles es su estilo de vida, actividades que realiza, intereses, opiniones, personalidad, ventajas deseadas del producto, usos que da al producto, ocasiones en que lo compra, frecuencia de compra, cantidad de compra, medios de pago (efectivo, transferencia, crédito), valores y creencias. También puede contar qué le gusta comer, si disfruta viajar u otras actividades que hagan parte de su vida. La idea es conocer al cliente como a un familiar cercano, entendiendo sus costumbres, motivaciones y forma de vivir, para saber mejor cómo ofrecerle el producto o servicio.
A67: CLIENTE
A68: Pequeñas y medianas empresas (PYMEs) con 5 a 100 empleados en manufactura, comercio, moda, gastronomía y servicios. Principalmente en Antioquia (Rionegro, Medellín y área metropolitana). Empresas con procesos operativos manuales que les consumen tiempo y les impiden crecer. | S68: Empresarios entre 30 y 55 años con visión de crecimiento, que toman decisiones de compra basadas en ROI claro y rapidez. No cuentan con especialistas en tecnología internos. Buscan soluciones accesibles con soporte local y en español.
A73: CONSUMIDOR
A74: El mismo gerente o dueño de la PYME, y los empleados operativos que ejecutan tareas manuales repetitivas: digitación de datos, atención a clientes por WhatsApp, generación de informes y creación de contenido para redes sociales.
A80: 2. PLANTEAMIENTO DEL PROBLEMA O NECESIDAD QUE SE PRETENDE SOLUCIONAR
A81: En este espacio identifique el dolor o la necesidad no resuelta del cliente o consumidor que solucionará al usar el producto o servicio. Este elemento busca que se responde a la pregunta ¿Cuál es el problema o necesidad que se pretende solucionar? ¿Cómo le estoy ayudando al cliente? Ojo! No es su problema personal o del grupo asociativo, sino el problema o necesidad del posible cliente del punto anterior.
A84: Las PYMEs colombianas destinan entre el 40% y el 60% de su tiempo operativo a tareas manuales repetitivas: ingreso de datos, gestión de pedidos, atención al cliente, creación de contenido y generación de informes. Esta ineficiencia les impide dedicar tiempo a actividades estratégicas de alto valor como innovación, expansión y servicio diferenciado. A diferencia de las grandes empresas, las PYMEs no tienen presupuesto para contratar equipos de tecnología propios ni acceso a soluciones de IA a precio asequible con soporte local. La brecha digital entre grandes corporaciones y PYMEs se amplía cada año, amenazando la competitividad del tejido empresarial colombiano.
A96: 3. LA COMPETENCIA (Quien más lo hace?)
A97: Siempre hay competencia, hay que reconocerlo y son esos que hacen lo mismo que queremos hacer, o los que con su producto o servicio reemplazan lo que queremos hacer, describa tres (3) competidores y en qué se diferencia de ellos.
A100: Nombre del competidor | I100: Localización geográfica (Departamento, Municipio) | R100: Producto o Servicio | X100: Precio (Solo colocar valor $) | AC100: Ventajas del competidor comparado con la iniciativa que se postula | AK100: Desventajas del competidor comparado con la iniciativa que se postula
A101: Agencias de marketing digital (locales) | I101: Antioquia, Medellín | R101: Gestión de redes sociales y pauta digital | X101: 2500000 | AC101: Presencia de marca y reconocimiento local consolidado | AK101: No ofrecen automatización real ni IA. Solo crean contenido, no optimizan procesos internos del negocio.
A102: Freelancers internacionales (Upwork, Workana) | I102: Nacional / Internacional (remoto) | R102: Automatizaciones puntuales con Make.com o Zapier | X102: 1500000 | AC102: Precios bajos y disponibilidad inmediata en plataformas digitales | AK102: Sin soporte presencial. Sin conocimiento del mercado colombiano. Alta rotación, sin continuidad ni garantía posventa.
A103: Consultoras TI (Pragma, Globant, Perficient) | I103: Bogotá / Medellín - Nacional | R103: Desarrollo de software y transformación digital corporativa | X103: 80000000 | AC103: Equipo amplio, respaldo de marca, proyectos complejos de gran escala | AK103: Precios y tiempos fuera del alcance de PYMEs. Proyectos de 3-12 meses mínimo. No accesibles para negocios pequeños.
A105: Conclusión: Según lo analizado, ¿Cuál considera que son esas ventajas competitivas que tiene la inciativa a postularse frente a la competencia?
A106: AI4U tiene ventaja competitiva clara en cuatro frentes: (1) VELOCIDAD: implementación en 3 a 14 días vs. meses de las consultoras. (2) PRECIO PYME: soluciones desde $2.5M accesibles para negocios colombianos. (3) SOPORTE LOCAL: acompañamiento presencial en Rionegro y Medellín, en español, con conocimiento del mercado antioqueño. (4) FILOSOFÍA HUMANÍSTICA: "no reemplazamos, potenciamos" — la IA trabaja junto al equipo, aumentando capacidades sin generar desempleo. Casos validados: Universidad EAFIT (formación docentes rurales en IA) y empresa TRUE moda (6 horas diarias liberadas en creación de contenido).
A110: 4. DESCRIPCIÓN DEL PROYECTO (Qué es lo que voy a ofrecer?)
A111: Aquí debe explicar en qué consiste su iniciativa y qué la hace diferente de las demás. Señale cuál es la ventaja que tiene frente a otros productos o servicios que ya existen en el mercado. Describa ese detalle especial, único o distinto que le agrega a su producto o servicio y que hace que el cliente lo prefiera, ya sea por su calidad, el precio justo, la forma en que se produce, el cuidado con que se entrega o cualquier otro aspecto que lo haga sobresalir, mejor que la competencia.
A114: El proyecto consiste en: | I114: AI4U diseña e implementa sistemas de Inteligencia Artificial personalizados para PYMEs colombianas, enfocados en automatizar procesos clave como ventas, atención al cliente, marketing y operaciones internas. A través de agentes inteligentes, chatbots, integraciones entre plataformas y automatización de flujos de trabajo, la empresa transforma tareas manuales, repetitivas y propensas a error en sistemas digitales que operan 24/7, permitiendo a las empresas ser más eficientes, rápidas y competitivas. Las soluciones se implementan en un tiempo estimado de 3 a 14 días, incluyendo diagnóstico, desarrollo, pruebas, capacitación al cliente y acompañamiento continuo para garantizar resultados sostenibles.
A115: AI4U no comercializa herramientas tecnológicas aisladas, sino que desarrolla sistemas completos adaptados a cada negocio, integrando tecnologías de vanguardia como OpenAI y Claude. Su enfoque combina velocidad de implementación, personalización y cercanía con el cliente, asegurando que cada solución tenga impacto real en la operación y en los resultados financieros.
A116: Ahora, de acuerdo con la sesión de entrenamiento, describa la propuesta de valor:
A117: Nuestro: | G117: AI4U — servicio especializado en implementación de sistemas de Inteligencia Artificial y automatización personalizados para empresas colombianas
A118: Ayuda: | G118: a PYMEs y empresas en crecimiento de AnPYMEs y empresas en crecimiento en Antioquia y Colombia que presentan alta carga operativa manual, procesos ineficientes y limitaciones para escalar sus operacionestioquia y Colombia con procesos operativos manuales y repetitivos
A119: Que: | G119: logran reducir hasta un 70% el tiempo dedicado a tareas operativas, aumentar su capacidad productiva sin incrementar costos de personal, mejorar la velocidad de respuesta al cliente y tomar decisiones estratégicas basadas en datos en tiempo real
A120: Mediante: | G120: el diseño e implementación de arquitecturas de IA personalizadas, construidas con tecnologías accesibles y robustas, implementadas en un periodo de 3 a 14 días, acompañadas de capacitación, soporte técnico continuo y mejora progresiva basada en datos
A122: 5. PRODUCTOS O SERVICIOS
A123: Relacione y describa los productos o servicios a ofrecer al cliente. Descríbalos, indique cual es la unidad de medida (Libras, Kilos...), presentación. Agrúpelos en únicamente tres (3) productos o servicios.
A127: Nombre del producto o servicio | K127: Descripción | Y127: Unidad de medida | AF127: Unidad de presentación al cliente
A128: Automatización Inteligente | K128: Diseño e implementación de sistemas de automatización basados en inteligencia artificial que optimizan procesos empresariales como ventas, marketing, atención al cliente y operaciones. Incluye integración de herramientas digitales, desarrollo de agentes inteligentes y monitoreo continuo para garantizar eficiencia, reducción de costos y escalabilidad del negocio. | Y128: Proyecto / Mensualidad | AF128: Servicio digital entregado mediante implementación remota, acceso a sistemas automatizados, dashboards de control y soporte continuo.
A132: 6. PROCESO TÉCNICO
A133: Explique de forma clara cómo se hace su producto o se presta el servicio, paso a paso desde el inicio hasta la entrega al cliente (por ejemplo: preparar el terreno o el lugar, comprar insumos, producir/sembrar, cuidar y controlar plagas, cosechar o elaborar, seleccionar, empacar, almacenar y transportar; en servicios: recibir al cliente, hacer la atención, revisar calidad y cobrar). Escriba cada actividad tal como ocurre, diciendo quién la hace, con qué herramienta o equipo y cuánto tiempo tarda; si aplica, mencione en qué épocas del año se realiza (temporadas). No olvide contar lo que lo hace diferente, como usar insumos amigables con el ambiente (fungicidas o controladores biológicos), buenas prácticas (ahorro de agua y energía, manejo de residuos), empaques retornables o recetas/procesos propios. Si corresponde, incluya medidas de higiene y seguridad que aplica en el proceso.
A138: En el siguiente cuadro colocar la información solicitada en las casillas en gris, del producto o servicio 1 descrito anteriormente
A139: =+A128 -> Automatización Inteligente
A140: Actividad a realizar (No solo coloque la actividad, descríbala) | O140: Tiempo para realizarla (Días, horas, minutos) | X140: Equipo o Maquinaria requerida | AF140: Quién realiza la actividad (Ej: Administrador, operario, veterinario, agrónomo)
A141: "1. Diagnóstico inicial del cliente Reunión para identificar procesos actuales, cuellos de botella y oportunidades de automatización. Se levanta información clave del negocio." | O141: 1 dia | X141: Computador, videollamada (Zoom/Meet), formularios digitales | AF141: Consultor IA / Administrador
A142: 2. Diseño de solución personalizada | O142: 2 dias | X142: Computador, software de diagramación, plataformas IA | AF142: Consultor IA / Administrador
A143: 3. Configuración e integración de herramientas | O143: 5 dias | X143: Computador, Make, APIs, servidores cloud | AF143: Consultor IA / Administrador
A144: 4. Pruebas y validación del sistema | O144: 2 dias | X144: Computador, entornos de prueba | AF144: Consultor IA / Administrador
A145: 5. Implementación y entrega al cliente | O145: 1 dia | X145: Computador, plataformas digitales, dashboards | AF145: Consultor IA / Administrador
A146: 6. Monitoreo y optimización continua | O146: permanente mensual | X146: Computador, herramientas de monitoreo, analytics | AF146: Consultor IA / Administrador
A151: CAPACIDAD INSTALADA PRODUCTO O SERVICIO 1: Es el cálculo de la cantidad máxima que se puede producir o atender del producto o servicio 1, con lo que tiene disponible, teniendo en cuenta sus herramientas, el tiempo de trabajo y el apoyo de las personas que participan en la actividad. No se calcula por persona, sino por todo lo que el negocio puede producir o atender en conjunto.
A152: Producción o servicios por hora (Número) | O152: Horas de trabajo día | X152: Días de trabajo en el mes | AF152: Total unidades al mes
A153: 0.05 | O153: 8 | X153: 22 | AF153: =+A153*O153*X153 -> 8.8
A155: En el siguiente cuadro colocar la información del producto o servicio 2 descrito anteriormente
A156: =+A129 -> 0
A157: Actividad a realizar (No solo coloque la actividad, descríbala) | O157: Tiempo para realizarla (Días, horas, minutos) | X157: Equipo o Maquinaria requerida | AF157: Quién realiza la actividad (Ej: Administrador, operario, veterinario, agrónomo)
A168: CAPACIDAD INSTALADA PRODUCTO O SERVICIO 2: Es el cálculo de la cantidad máxima que usted puede producir o atender del producto o servicio 2 con lo que tiene disponible, teniendo en cuenta sus herramientas, el tiempo de trabajo y el apoyo de las personas que participan en la actividad. No se calcula por persona, sino por todo lo que el negocio puede producir o atender en conjunto.
A169: Producción o servicios por hora (Número) | O169: Horas de trabajo día | X169: Días de trabajo en el mes | AF169: Total unidades al mes
AF170: =+A170*O170*X170 -> 0
A172: En el siguiente cuadro colocar la información del producto o servicio 3 descrito anteriormente
A173: =+A130 -> 0
A174: Actividad a realizar (No solo coloque la actividad, descríbala) | O174: Tiempo para realizarla (Días, horas, minutos) | X174: Equipo o Maquinaria requerida | AF174: Quién realiza la actividad (Ej: Administrador, operario, veterinario, agrónomo)
A185: CAPACIDAD INSTALADA PRODUCTO O SERVICIO 3: Es el cálculo de la cantidad máxima que usted puede producir o atender del producto o servicio 3 con lo que tiene disponible, teniendo en cuenta sus herramientas, el tiempo de trabajo y el apoyo de las personas que participan en la actividad. No se calcula por persona, sino por todo lo que el negocio puede producir o atender en conjunto.
A186: Producción o servicios por hora (Número) | O186: Horas de trabajo día | X186: Días de trabajo en el mes | AF186: Total unidades al mes
AF187: =+A187*O187*X187 -> 0
A189: 7. TRÁMITES LEGALES (PERMISOS Y LICENCIAS)
A191: ¿Cuál es el tipo de registro formal que tendrá la iniciativa? Es importante analizar de acuerdo con la actividad económica a realizar y lo planteado en la iniciativa, cuál es la mejor forma de registro formal si la iniciativa llega a ser beneficiaria de los recursos del Fondo Emprender
A194: Solo debe marcar una opción | S194: Marque con X
A195: Persona Natural
A196: Persona Natural con Establecimiento de Comercio
...

Sheet Topes Montos
A1: Salario mínimo mensual vigente | B1: 1750905
A3: Individual
A4: integrantes individual mínimo | B4: integrantes individual máximo | C4: Monto Mínimo | D4: Monto Máximo | E4: Empleos Minimos | H4: Smmlv mínimo | I4: Smmlv máximo
A5: 1 | B5: 1 | C5: 0 | D5: 73538010 | E5: 1 | H5: 0 | I5: 42
A6: 1 | B6: 1 | C6: 75288915 | D6: 98050680 | E6: 3 | H6: 43 | I6: 56
A7: 1 | B7: 1 | C7: 99801585 | D7: 122563350 | E7: 5 | H7: 57 | I7: 70
A9: Asociativo
A10: Asociativos Cantidad Integrantes mínimos | B10: Asociativos Cantidad Integrantes máximo | C10: Monto Mínimo | D10: Monto Máximo | E10: Empleos Minimos | H10: Smmlv mínimo | I10: Smmlv máximo
A11: 5 | B11: 9 | C11: 350181000 | D11: 523520595 | E11: 7 | H11: 200 | I11: 299
A12: 10 | B12: 14 | C12: 525271500 | D12: 698611095 | E12: 8 | H12: 300 | I12: 399
A13: 15 | B13: 9999 | C13: 700362000 | D13: 875452500 | E13: 10 | H13: 400 | I13: 500
A14: 20 | B14: 20 | C14: 700362000 | D14: 1050543000 | E14: 7 | H14: 400 | I14: 600
A15: 21 | B15: 26 | C15: 1050543000 | D15: 1575814500 | E15: 8 | H15: 600 | I15: 900
A16: 27 | B16: 9999 | C16: 1575814500 | D16: 1925995500 | E16: 10 | H16: 900 | I16: 1100
A18: Tipo asociatividad (Individual o asociativo) | B18: =+Proyecto!M28 -> Individual
A20: integrantes presentados | B20: =+Proyecto!AE479 -> 1 | C20: Recursos solicitados $$ | D20: =+Proyecto!AE480 -> 75115200 | E20: Empleos propuestos | F20: =+Proyecto!AE481 -> 3
A21: Cumple con integrantes | B21: {=IF(B18="Individual",IF(AND(B20>=A5,B20<=B5),"Cumple integrantes permitidos","No cumple # integrantes permitidos"),IF(SUMPRODUCT((B20>=A11:A16)*(B20<=B11:B16))>0,"Cumple integrantes permitidos","No cumple # integrantes permitidos"))} -> Cumple integrantes permitidos | C21: Cumple con los recursos solicitado | D21: {=IF(B18="Individual",IF(AND(B20>=A5,B20<=B5,D20>=C5,D20<=D5),"Cumple recursos para el número de integrantes registrados","No cumple rango de recursos para el número de integrantes registrados"),IF(SUMPRODUCT((B20>=A11:A16)*(B20<=B11:B16)*(D20>=C11:C16)*(D20<=D11:D16))>0,"Cumple recursos para el número de integrantes registrados","No cumple rango de recursos para el número de integrantes registrados"))} -> No cumple rango de recursos para el número de integrantes registrados | E21: Cumple con Empleos propuestos | F21: {=IF(B18="Individual",IF(AND(B20>=A5,B20<=B5,F20>=E5),"Cumple empleos a generar","No cumple empleos mínimos requeridos para el número de integrantes"),IF(SUMPRODUCT((B20>=A11:A16)*(B20<=B11:B16)*(F20>=E11:E16))>0,"Cumple empleos a generar","No cumple empleos mínimos requeridos"))} -> Cumple empleos a generar
A23: Cumple con Recursos, integrantes y empleos | B23: {=IF(B18="Individual",IF(AND(B20>=A5,B20<=B5,D20>=C5,D20<=D5,F20>=E5),"Cumple","No cumple condiciones para la postulación"),IF(SUMPRODUCT((B20>=A11:A16)*(B20<=B11:B16)*(D20>=C11:C16)*(D20<=D11:D16)*(F20>=E11:E16))>0,"Cumple","No cumple condiciones para la postulación"))} -> No cumple condiciones para la postulación
B33: {=IF(B18="Individual",IF(AND(B20>=INDEX(A5:A7,#REF!),B20<=INDEX(B5:B7,#REF!),D20>=INDEX(C5:C7,#REF!),D20<=INDEX(D5:D7,#REF!),#REF!>=INDEX(E5:E7,#REF!)),"Cumple condición de empleos,montos y recursos","No cumple condiciones"),IF(AND(B20>=INDEX(A11:A16,#REF!),B20<=INDEX(B11:B16,#REF!),D20>=INDEX(C11:C16,#REF!),D20<=INDEX(D11:D16,#REF!),#REF!>=INDEX(E11:E16,#REF!)),"Cumple condición de empleos,montos y recursos","No cumple B21,D21 y F21"))} -> #REF!
A36: Rubros Financiables
A37: Adecuaciones o remodelaciones estructurales
A38: Adecuaciones técnicas
A39: Adquisición de maquinaria, equipos y software
A40: Adquisición e implementación de franquicias mediante el modelo de franquicias
A41: Adquisición o arriendo de bienes muebles y vehículos automotores
A42: Insumos para el ciclo productivo
A43: Pago de salarios u honorarios
A44: Permisos, licencias y registros
A45: Tasas para el registro de derechos de propiedad intelectual o industrial

Sheet Integrantes Iniciativa
C4: INICIATIVA PRODUCTIVA, UNIDAD PRODUCTIVA, UNIDAD ECONÓMICA, MODELO O PLAN DE NEGOCIO A CREAR
C7: Por favor diligencie toda la información de las personas que postulan la iniciativa, tanto para proyectos individuales (1) como asociativos
C9: Frente al elemento "Función principal" de cada uno de los miembros de la iniciativa, los cuales deben clasificarse así:
C10: 1. Gestión y Administración: - Establecer y mantener una estructura de gobierno eficaz. - Designar y supervisar a los miembros de la junta directiva u órganos de gobierno. - Garantizar el cumplimiento de los estatutos, reglamentos internos y normativas legales aplicables. 2. Transparencia y Responsabilidad: - Mantener registros precisos y transparentes de las actividades y decisiones de la iniciativa - Presentar informes financieros y de actividades de manera periódica a los miembros y otras partes interesadas. - Actuar de manera 3. Gestión de Recursos: - Administrar eficientemente los recursos financieros y materiales de la iniciativa - Garantizar que los fondos se utilicen de manera adecuada y en línea con los objetivos de la iniciativa. - Buscar fuentes de financiamiento sostenibles para apoyar las actividades de la iniciativa ética y responsable en todas las actividades de la iniciativa. 4. Relaciones con los Miembros y la Comunidad: - Fomentar la participación activa y el compromiso de los miembros en las actividades de la iniciativa. - Mantener una comunicación abierta y efectiva con los miembros, socios y otras partes interesadas. - Colaborar con otras organizaciones y entidades para promover los objetivos de la iniciativa. 5. Cumplimiento Legal: - Cumplir con todas las leyes y regulaciones aplicables a la iniciativa. - Presentar informes fiscales y legales requeridos por las autoridades competentes. - Proteger los derechos y el bienestar de los miembros, empleados y otras partes interesadas.
C13: Diligenciar para caso individual y asociativo
B14: SE HAN DILIGENCIADO: | F14: =+COUNTA(P17:P116,P103) -> 1 | G14: INTEGRANTES DE LA INICIATIVA A CREAR
B15: INFORMACIÓN DE LOS INTEGRANTES DE LA INICIATIVA (Diligencie todas las casillas por integrante)
B16: No | C16: Nombres y Apellidos Completos | D16: Tipo de Documento de identidad | E16: Número de documento | F16: Rol dentro del grupo | G16: Participación % en la toma de decisiones | H16: Función principal | I16: Género | J16: Edad | L16: Caracterización | O16: Teléfono Contacto | P16: Ingresos mensuales promedio actuales
B17: 1 | C17: Mariano García Posada | D17: CC | E17: 8026979 | F17: CEO / Desarrollador Fullstack IA | G17: 1 | H17: Gestión y Administración | I17: Masculino | J17: 41 | L17: Ninguno | O17: 3218175744 | P17: 4000000 | R17: Tipo de documento | T17: Función Principal | V17: Genero | X17: Caracterización
B18: 2 | R18: CC | T18: Gestión y Administración | V18: Femenino | X18: Adolescentes en Conflicto con la Ley Penal
B19: 3
B20: 4
B21: 5
B22: 6
B23: 7
B24: 8
B25: 9
B26: 10
B27: 11
B28: 12
B29: 13
B30: 14
... B38: 22
B39: 23 | R39: CE | T39: Transparencia y Responsabilidad: | V39: Masculino | X39: Adolescente Trabajador
B40: 24 | T40: Gestión de Recursos | V40: Otro | X40: Adolescentes y Jóvenes Vulnerables
B41: 25 | T41: Relaciones con los Miembros y la Comunidad | X41: Afrocolombianos
B42: 26 | T42: Cumplimiento Legal | X42: Campesino
B43: 27 | X43: Desplazado por fenómenos naturales
B44: 28 | X44: Economía Popular
B45: 29 | X45: Migrantes que retornan al país
B46: 30 | X46: Mujer cabeza de hogar
B47: 31 | X47: Negritudes
B48: 32 | X48: Ninguno
B49: 33 | X49: Palenqueros
B50: 34 | X50: Participanes del programa de reintegración - Reintegrados (ARN)
B51: 35 | X51: Personas en Proceso de Reincorporación
B52: 36 | X52: Población LGBTI
B53: 37 | X53: Población con discapacidad
B54: 38 | X54: Población indígena
... B63: 47 | X63: Víctima de violencia
B64: 48
B65: 49
B66: 50
B67: 51
B68: 52
B69: 53
B70: 54
B71: 55
B72: 56
B73: 57
B74: 58
B75: 59
... B116: 100

Sheet Modelo Financiero
B5: TOTAL INICIATIVA - VALOR SOLICITADO AL FONDO EMPRENDER | C5: =+Proyecto!AE480 -> 75115200
B6: Diligenciar la tasa de descuento | D6: DILIGENCIAR
B8: =+Proyecto!M28 -> Individual
B9: ESTADO DE RESULTADOS | D9: AÑO 1 | E9: AÑO 2 | F9: AÑO 3 | G9: AÑO 4 | H9: AÑO 5
B10: Ventas | D10: =+Proyecto!K280+Proyecto!K298+Proyecto!K316 -> 63000000 | E10: =+Proyecto!W280+Proyecto!W298+Proyecto!W316 -> 161700000 | F10: =+Proyecto!AI280+Proyecto!AI298+Proyecto!AI316 -> 254100000 | G10: =+Proyecto!AU280+Proyecto!AU298+Proyecto!AU316 -> 335412000 | H10: =+Proyecto!BG280+Proyecto!BG298+Proyecto!BG316 -> 450942800
B11: Materia Prima | D11: =+(Proyecto!G280*Proyecto!AE347)+(Proyecto!AE356*Proyecto!G298)+(Proyecto!G316*Proyecto!AE365) -> 15300000 | E11: =((Proyecto!S280)*(Proyecto!AE347*(1+Proyecto!F251)))+(Proyecto!S298*(Proyecto!AE356*(1+Proyecto!F251)))+(Proyecto!S316*(Proyecto!AE365*(1+Proyecto!F251))) -> 39270000 | F11: =+(Proyecto!AE280*(Proyecto!AE347*(1+Proyecto!F251+Proyecto!I251)))+(Proyecto!AE298*(Proyecto!AE356*(1+Proyecto!F251+Proyecto!I251)))+(Proyecto!AE316*(Proyecto!AE365*(1+Proyecto!F251+Proyecto!I251))) -> 61200000 | G11: =+(Proyecto!AQ280*(Proyecto!AE347*(1+Proyecto!F251+Proyecto!I251+Proyecto!L251)))+(Proyecto!AQ298*(Proyecto!AE356*(1+Proyecto!F251+Proyecto!I251+Proyecto!L251)))+(Proyecto!AQ316*(Proyecto!AE365*(1+Proyecto!F251+Proyecto!I251+Proyecto!L251))) -> 79560000 | H11: =+(Proyecto!BC280*(Proyecto!AE347*(1+Proyecto!F251+Proyecto!I251+Proyecto!L251+Proyecto!O251)))+(Proyecto!BC298*(Proyecto!AE356*(1+Proyecto!F251+Proyecto!I251+Proyecto!L251+Proyecto!O251)))+(Proyecto!BC316*(Proyecto!AE365*(1+Proyecto!F251+Proyecto!I251+Proyecto!L251+Proyecto!O251))) -> 104720000
B12: Mano de Obra | D12: =+(Proyecto!AK414*Proyecto!AP414)+(Proyecto!AK415*Proyecto!AP415)+(Proyecto!AK416*Proyecto!AP416)+(Proyecto!AK417*Proyecto!AP417)+(Proyecto!AK418*Proyecto!AP418)+(Proyecto!AK419*Proyecto!AP419)+(Proyecto!AK420*Proyecto!AP420)+(Proyecto!AK421*Proyecto!AP421)+(Proyecto!AK422*Proyecto!AP422)+(Proyecto!AK423*Proyecto!AP423) -> 29251200 | E12: =+(Proyecto!AK424*(1+Proyecto!F251))*12 -> 84648960 | F12: =+E12*(1+Proyecto!I251) -> 93113856 | G12: =+F12*(1+Proyecto!L251) -> 1.0242524e+08 | H12: =+G12*(1+Proyecto!O251) -> 1.1266777e+08
B13: Costos Fijos | D13: =+Proyecto!AE332 -> 9600000 | E13: =+D13*(1+Proyecto!F251) -> 10560000 | F13: =+(E13*(1+Proyecto!I251)) -> 11616000 | G13: =+(F13*(1+Proyecto!L251)) -> 12777600 | H13: =+(G13*(1+Proyecto!O251)) -> 14055360
B14: Permisos y Licencias | D14: =+Proyecto!Z215 -> 800000
B15: Utilidad Bruta | D15: =+D10-D11-D13-D12-D14 -> 8048800 | E15: =+E10-E11-E13-E12-E14 -> 27221040 | F15: =+F10-F11-F13-F12-F14 -> 88170144 | G15: =+G10-G11-G13-G12-G14 -> 1.4064916e+08 | H15: =+H10-H11-H13-H12-H14 -> 2.1949967e+08
B16: Gastos de Administración y Ventas | D16: =+Proyecto!Y392 -> 7200000 | E16: =+Proyecto!AE392 -> 7920000 | F16: =+Proyecto!AK392 -> 8712000 | G16: =+Proyecto!AQ392 -> 9583200 | H16: =+Proyecto!AW392 -> 10541520
B17: Utilidad Operativa | D17: =+D15-D16 -> 848800 | E17: =+E15-E16 -> 19301040 | F17: =+F15-F16 -> 79458144 | G17: =+G15-G16 -> 1.3106596e+08 | H17: =+H15-H16 -> 2.0895815e+08
B18: Impuesto de Renta | D18: =+IF($B$8="Asociativo",(D17*0.33),0) -> 0 | E18: =+IF($B$8="Asociativo",(E17*0.33),0) -> 0 | F18: =+IF($B$8="Asociativo",(F17*0.33),0) -> 0 | G18: =+IF($B$8="Asociativo",(G17*0.33),0) -> 0 | H18: =+IF($B$8="Asociativo",(H17*0.33),0) -> 0
B19: Utilidad Neta Final | D19: =+D17-D18 -> 848800 | E19: =+E17-E18 -> 19301040 | F19: =+F17-F18 -> 79458144 | G19: =+G17-G18 -> 1.3106596e+08 | H19: =+H17-H18 -> 2.0895815e+08
B21: *Nota: Si su proyecto es individual no le será calculado valor por Impuesto de Renta
B23: FLUJO DE CAJA
B24: Flujo de caja para evaluación | C24: =-'Modelo Financiero'!C5 -> -75115200 | D24: =+D17 -> 848800 | E24: =+E17 -> 19301040 | F24: =+F17 -> 79458144 | G24: =+G17 -> 1.3106596e+08 | H24: =+H17 -> 2.0895815e+08
B26: TIR | C26: VALOR PRESENTE NETO
B27: =+IRR(C24:H24) -> 0.55469781 | C27: =NPV(C6,C24:H24) -> 3.645169e+08

Sheet Resumen
A6: Línea de financiación | B6: ID Proyecto | C6: Convocatoria | D6: Departamento | E6: Municipio | F6: Nombre de la Iniciativa | G6: Sector | H6: Actividad Económica | I6: Datos Líder Proyecto | J6: Documento de identidad Líder Proyecto | K6: Tipo de proyecto | L6: Monto Solicitado | M6: No. Asociados | N6: Empleos a crear | O6: Empleos a retener N/A | P6: Total Empleos | Q6: Eventos de Mercadeo a cumplir | R6: Contrapartidas a cumplir | S6: Empleos indirectos | T6: TIR
A7: Crear | B7: =+Proyecto!T8 -> 0 | C7: =+Proyecto!T9 -> 0 | D7: =Proyecto!T19 -> Antioquia | E7: =Proyecto!AC19 -> Rionegro | F7: =Proyecto!B19 -> AI4U | G7: =Proyecto!L25 -> INFORMACIÓN_Y_COMUNICACIONES | H7: =Proyecto!Z25 -> 6209 Otras actividades de tecnologías de información y actividades de servicios informáticos | I7: =Proyecto!B15 -> Mariano García Posada | J7: =Proyecto!AC15 -> 8026979 | K7: =+Proyecto!M28 -> Individual | L7: =Proyecto!AE480 -> 75115200 | M7: =Proyecto!AN28 -> 1 | N7: =Proyecto!K538 -> 3 | O7: 0 | P7: =+N7 -> 3 | Q7: =+Proyecto!K539 -> 1 | R7: =+Proyecto!K540 -> 5 | S7: =+Proyecto!AC426 -> 2 | T7: =+'Modelo Financiero'!B27 -> 0.55469781

Sheet Hoja2
B3: SI | C3: CC | D3: Aporte Emprendedor
B4: NO | C4: CE | D4: Fondo Emprender
B6: Femenino
B7: Masculino | F7: Adolescentes en Conflicto con la Ley Penal
B8: No Binario | F8: Adolescente Trabajador
B9: Trans | F9: Adolescentes y Jóvenes Vulnerables
F10: Afrocolombianos
B11: Gestión y Administración | F11: Campesino
B12: Transparencia y Responsabilidad | F12: Cuidadores
B13: Gestión de Recursos | F13: Desplazado por fenómenos naturales
B14: Relaciones con los Miembros y la Comunidad | F14: Economía Popular
B15: Cumplimiento Legal | F15: Migrantes que retornan al país
F16: Mujer cabeza de hogar | H16: =20*(10000*(1+3.3%)) -> 206600 | J16: 30 | K16: 10000 | L16: =+Proyecto!F251+Proyecto!I251 -> 0.2
F17: Negritudes | H17: =10*(20000*(1+3.3%)) -> 206600 | J17: 15 | K17: 20000 | L17: =+L16 -> 0.2
B18: Contrato Laboral a término fijo | F18: Ninguno | H18: =40*(1000*(1+3.3%)) -> 41320 | J18: 60 | K18: 1000 | L18: =+L16 -> 0.2
B19: Contrato Laboral a término indefinido | F19: Palenqueros | H19: =+H16+H17+H18 -> 454520
B20: Contrato por obra o Labor | F20: Participanes del programa de reintegración - Reintegrados (ARN) | J20: =+(J16*(K16*(1+L16))) -> 360000
B21: Jornal | F21: Personas en Proceso de Reincorporación | J21: =+(J17*(K17*(1+L17))) -> 360000
B22: Prestación de servicios | F22: Población LGBTI | J22: =+(J18*(K18*(1+L18))) -> 72000
F23: Población con discapacidad | J23: =+J20+J21+J22 -> 792000
B24: 1 | F24: Población indígena
B25: 2 | F25: Población víctima de minas antipersona
B26: 3 | F26: Pueblo ROM | J26: =5*12 -> 60
B27: 4 | F27: Raizales | J27: =+J26*(1+3.33%) -> 61.998
B28: 5 | D28: Contrato Laboral a término indefinido | F28: Remitidos por programa de adaptación laboral - PAL
B29: 6 | D29: Prestación de servicios | F29: Soldados campesinos
B30: 7 | D30: Contrato por obra o Labor | F30: Tercera edad
B31: 8 | D31: Jornal | F31: Veteranos
B32: 9 | F32: Víctima de otros hechos victimizantes
B33: 10 | F33: Víctima de violencia
B34: 11 | F34: Víctimas Sobrevivientes con Agentes Químicos
B35: 12
F37: 50000000
F38: 50700000
F39: 59000000
F40: 60000000
